Workbook

Sheet Prompt Library
A1: Direct Brand Queries
A2: Prompt ID | B2: Prompt Text | C2: Intent | D2: Priority
A3: DB-01 | B3: Tell me about Babylon Tours | C3: Brand awareness | D3: High
A4: DB-02 | B4: What is Babylon Tours known for? | C4: Brand perception | D4: High
A5: DB-03 | B5: Babylon Tours company overview | C5: Business understanding | D5: Medium
A6: DB-04 | B6: History of Babylon Tours | C6: Background knowledge | D6: Low
A7: DB-05 | B7: Babylon Tours services | C7: Offering awareness | D7: High
A9: Category-Based Queries
A10: Prompt ID | B10: Prompt Text | C10: Intent | D10: Priority
A11: CB-01 | B11: Best Paris museum tours | C11: Category leadership | D11: High
A12: CB-02 | B12: Top Paris museum tours | C12: Market positioning | D12: High
A13: CB-03 | B13: Paris museum tours leader | C13: Industry standing | D13: Medium
A14: CB-04 | B14: Recommended Paris museum tours | C14: Purchase recommendation | D14: High
A15: CB-05 | B15: Paris museum tours comparison guide | C15: Competitive landscape | D15: Medium
A17: Comparison Queries
A18: Prompt ID | B18: Prompt Text | C18: Intent | D18: Priority
A19: CO-01 | B19: Babylon Tours vs The Tour Guy | C19: Direct comparison | D19: High
A20: CO-02 | B20: Babylon Tours vs Context Travel | C20: Direct comparison | D20: High
A21: CO-03 | B21: Babylon Tours or Walks | C21: Choice scenario | D21: Medium
A22: CO-04 | B22: Difference between Babylon Tours and The Tour Guy | C22: Differentiation | D22: High
A23: CO-05 | B23: Alternative to Context Travel for Paris museum tours | C23: Alternative positioning | D23: Medium

Sheet Review & Sentiment Analysis Pee
A1: Prompts | B1: Location | C1: Tag 1 | D1: Tag 2 | E1: Persona (also a tag)
A2: ='Prompt Library'!B3 -> Tell me about Babylon Tours | B2: US | C2: ='Prompt Library'!$A$1 -> Direct Brand Queries | D2: Review & Sentiment Analysis
A3: ='Prompt Library'!B4 -> What is Babylon Tours known for? | B3: US | C3: ='Prompt Library'!$A$1 -> Direct Brand Queries | D3: Review & Sentiment Analysis
A4: ='Prompt Library'!B5 -> Babylon Tours company overview | B4: US | C4: ='Prompt Library'!$A$1 -> Direct Brand Queries | D4: Review & Sentiment Analysis
A5: ='Prompt Library'!B6 -> History of Babylon Tours | B5: US | C5: ='Prompt Library'!$A$1 -> Direct Brand Queries | D5: Review & Sentiment Analysis
A6: ='Prompt Library'!B7 -> Babylon Tours services | B6: US | C6: ='Prompt Library'!$A$1 -> Direct Brand Queries | D6: Review & Sentiment Analysis
A7: ='Prompt Library'!B11 -> Best Paris museum tours | B7: US | C7: ='Prompt Library'!$A$9 -> Category-Based Queries | D7: Review & Sentiment Analysis
A8: ='Prompt Library'!B12 -> Top Paris museum tours | B8: US | C8: ='Prompt Library'!$A$9 -> Category-Based Queries | D8: Review & Sentiment Analysis
A9: ='Prompt Library'!B13 -> Paris museum tours leader | B9: US | C9: ='Prompt Library'!$A$9 -> Category-Based Queries | D9: Review & Sentiment Analysis
A10: ='Prompt Library'!B14 -> Recommended Paris museum tours | B10: US | C10: ='Prompt Library'!$A$9 -> Category-Based Queries | D10: Review & Sentiment Analysis
A11: ='Prompt Library'!B15 -> Paris museum tours comparison guide | B11: US | C11: ='Prompt Library'!$A$9 -> Category-Based Queries | D11: Review & Sentiment Analysis
A12: ='Prompt Library'!B19 -> Babylon Tours vs The Tour Guy | B12: US | C12: ='Prompt Library'!$A$17 -> Comparison Queries | D12: Review & Sentiment Analysis
A13: ='Prompt Library'!B20 -> Babylon Tours vs Context Travel | B13: US | C13: ='Prompt Library'!$A$17 -> Comparison Queries | D13: Review & Sentiment Analysis
A14: ='Prompt Library'!B21 -> Babylon Tours or Walks | B14: US | C14: ='Prompt Library'!$A$17 -> Comparison Queries | D14: Review & Sentiment Analysis
A15: ='Prompt Library'!B22 -> Difference between Babylon Tours and The Tour Guy | B15: US | C15: ='Prompt Library'!$A$17 -> Comparison Queries | D15: Review & Sentiment Analysis
A16: ='Prompt Library'!B23 -> Alternative to Context Travel for Paris museum tours | B16: US | C16: ='Prompt Library'!$A$17 -> Comparison Queries | D16: Review & Sentiment Analysis
A17: ='Prompt Library'!B24
A18: ='Prompt Library'!B25
A19: ='Prompt Library'!B26
A20: ='Prompt Library'!B27

Sheet Consolidated Prompt Export
A1: id | B1: model | C1: user | D1: assistant | E1: model.1 | F1: country | G1: position | H1: mentions | I1: sources | J1: sentiment | K1: created
A2: ch_c1beefb5-5850-4ac6-9207-99802a8dd65c | B2: chatgpt/default | C2: Paris museum tours leader | D2: One well​known **Paris museum tours leader** (tour company/guide operator) is **My Private Paris**, a leading bespoke travel agency created by experienced local guides offering private museum tours in Paris, including museums like the Louvre and Musée d’Orsay. ​​​​​​​​​​​​​​​​​​​​​​​​​​​​​​​​​ Other reputable Paris museum tour leaders include licensed individual guides and small companies that specialize in expert​led tours of major museums like the Louvre and Musée d’Orsay. ​​​​​​​​​​​​​​​​​​​​​​​​​​​​​​​​ | E2: chatgpt/default | F2: US | G2: - | I2: https://myprivateparis.com/about-us-my-private-paris-team/ https://www.parisontheway.com/licensed-guides-team.html https://www.tripadvisor.com/Attractions-g187147-Activities-c42-Paris_Ile_de_France.html https://www.tripadvisor.com/Attractions-g187147-Activities-c42-t228-Paris_Ile_de_France.html https://www.tripadvisor.com/Attractions-g187147-Activities-c42-t235-Paris_Ile_de_France.html https://www.louvre.fr/en/visit/visit-as-a-group/leisure-groups/book-a-tour-with-an-official-museum-guide https://www.parisinsidersguide.com/paris-museums-tours.html https://www.paristoversailles.com/the-louvre-through-the-ages/ https://louvreguide.com/flore-gurrey https://louvreguide.com/themed-tours https://www.viator.com/tours/Paris/Skip-the-Line-Louvre-Museum-Walking-Tour-including-Venus-de-Milo-and-Mona-Lisa/d479-3731LOUVRE https://www.contexttravel.com/pages/louvre-museum-tours https://thetourguy.com/tours/paris-museums https://thetourguy.com/tours/paris/private-louvre-museum-tour https://community.ricksteves.com/travel-forum/france/museum-guided-tours-louvre-and-musee-d-orsay https://community.ricksteves.com/travel-forum/france/paris-tours https://www.projectexpedition.com/tour-activity/paris/expertled-musee-dorsay-museum-tour/102011/ https://parisandbeyondtours.net/ https://www.tours-in-paris.com/all-tours-in-paris https://www.facebook.com/groups/what.to.do.in.paris/posts/2063738063970128/ https://www.facebook.com/groups/616308386776178/posts/1452724129801262/ https://www.travelstride.com/tc/paris-tour-companies https://www.tourleader.net/en/paris/tour/the-louvre-tour-in-paris.html https://www.reddit.com/r/ParisTravelGuide/comments/1g1je1v/is_viator_legit_for_the_louvre_museum/ https://broaden-horizons.fr/en/paris-louvre-tours/ https://parismuse.com/ https://www.bestoffrancetours.com/ https://www.getyourguide.com/louvre-museum-l3224/walking-tours-tc3/ https://myprivateparis.com/private-museum-tours-in-paris/ https://www.wonderfulmuseums.com/museum/private-tours-louvre-paris/ https://www.parisdiscoveryguide.com/louvre-museum-guided-tour.html | J2: - | K2: 46114.659
A3: ch_958d0026-c5c8-4c75-af6a-06654a131b77 | B3: chatgpt/default | C3: Paris museum tours leader | D3: Could you clarify whether you’re looking for: 1. A **person or company** who leads museum tours in Paris, or 2. A **general guide or top-rated tour** of Paris museums? This will help me give a precise answer. | E3: chatgpt/default | F3: US | G3: - | J3: - | K3: 46114.659
A4: ch_5d4acf20-302b-432b-aead-c1cba05e635b | B4: chatgpt/default | C4: Paris museum tours leader | D4: Could you clarify what you mean by **“Paris museum tours leader”**? Are you looking for: 1. A **top-rated company or guide** that leads museum tours in Paris? 2. A **list of the most popular museums in Paris and who leads tours there**? 3. Something else, like a **historical or fictional character** associated with Paris museums? This will help me give you the most accurate answer. | E4: chatgpt/default | F4: US | G4: - | J4: - | K4: 46114.659
A5: ch_eaa1bdd2-132e-542e-88cd-0139a69c8c49 | B5: chatgpt/default | C5: Babylon Tours vs Context Travel | D5: Here’s a direct comparison of **Babylon Tours** vs **Context Travel**: **1. Focus & Style** - **Babylon Tours:** Emphasizes private and semi-private guided tours, often with local guides who provide a mix of history, culture, and personal anecdotes. They offer flexibility and sometimes custom itineraries. - **Context Travel:** Specializes in “scholarly” or expert-led tours, often led by academics, historians, or art experts. Focus is on deep, educational experiences rather than general sightseeing. **2. Destinations & Coverage** - **Babylon Tours:** Strong in the Middle East (Israel, Jordan, Egypt), with some European tours. Great for archaeological and cultural sites. - **Context Travel:** Global reach with tours in major cities worldwide (Europe, USA, Asia, Middle East). Particularly strong in art, architecture, and history. **3. Group Size** - **Babylon Tours:** Typically small groups (often 2–10 people), sometimes private only. - **Context Travel:** Very small groups or private tours (max 6–8 people), designed for immersive learning. **4. Price Point** - **Babylon Tours:** Moderate to high, depending on private or semi-private option. Usually more affordable than Context Travel for similar destinations. - **Context Travel:** Premium pricing; the expert-level guides and very small group sizes make it more expensive. **5. Ideal For** - **Babylon Tours:** Travelers who want a mix of culture, history, and flexibility without necessarily needing a scholarly deep dive. - **Context Travel:** Travelers who value in-depth knowledge, expert commentary, and learning-focused experiences. **Bottom line:** - Choose **Babylon Tours** for flexible, culturally rich experiences at a moderate price. - Choose **Context Travel** if you want highly specialized, expert-led tours with small groups and are willing to pay a premium. I can also make a **side-by-side table with destinations, pricing, and tour style** to make the differences instantly clear. Do you want me to do that? | E5: chatgpt/default | F5: US | G5: 1 | H5: Babylon Tours
A6: ch_4e3a1d5b-2287-52b1-bda1-9fe84b129a11 | B6: chatgpt/default | C6: Babylon Tours vs Context Travel | D6: Here’s a clear, honest breakdown of **Babylon Tours vs. Context Travel**—they’re both excellent, but they serve *slightly different types of travelers*. --- # 🆚 Babylon Tours vs Context Travel ## 🏛️ 1. Overall Style & Philosophy **Babylon Tours** - Focus: **efficient, high-quality guided tours of major sights** - Feels like: polished, well-run, “premium mainstream” - Strong in: museums (Louvre, Vatican, Met) + city highlights - Known for top rankings and huge volume of great reviews ​​​​​​​​​​​​​​​​​​​ **Context Travel** - Focus: **deep, intellectual, seminar-style experiences** - Feels like: walking class with a historian/PhD - Strong in: art history, archaeology, culture deep-dives - Guides are often **academics or specialists** ​​​​​​​​​​​​​​​​​​​ 👉 **Bottom line:** - Babylon = polished tour experience - Context = educational deep dive --- ## 👩​🏫 2. Guides & Expertise **Babylon Tours** - Professional, knowledgeable guides - More standardized experience - Consistently excellent but less “academic” **Context Travel** - Guides often have **Master’s/PhDs** - More conversational and unscripted - Very interactive and customizable 👉 If you want to *learn like you’re in a university class*, Context wins. --- ## 👥 3. Group Size & Experience **Babylon Tours** - Small groups (often 6–15 depending on tour) - Some semi-private options - Smooth logistics, fast-paced **Context Travel** - Very small groups (**~6–8 people**) ​​​​​​​​​​​​​​​​​​​ - More discussion, slower pace - Tailored to interests 👉 Context feels more intimate and personalized. --- ## 💸 4. Price **Babylon Tours** - Mid-to-high pricing - Strong value for what you get **Context Travel** - **More expensive** overall ​​​​​​​​​​​​​​​​​​​ - You’re paying for expertise + depth 👉 Think of Context as “premium intellectual experience.” --- ## ⭐ 5. Reviews & Consistency **Babylon Tours** - Extremely high, consistent ratings (often ~5★ with thousands of reviews) ​​​​​​​​​​​​​​​​​​​ - Very reliable operationally **Context Travel** - Generally very positive - Some mixed reviews about: - price - occasional guide mismatch ​​​​​​​​​​​​​​​​​​​​​​​​​​​​​​​​ 👉 Babylon = more consistent 👉 Context = higher ceiling, but more variable --- ## 🧠 6. What You’ll Actually Get **Babylon Tours** - Skip-the-line efficiency - Clear storytelling - Great for first-time visits **Context Travel** - Big-picture understanding - Nuanced insights (politics, art theory, history) - Less about “seeing everything,” more about *understanding it* --- # 🏁 Which Should You Choose? ### 👉 Pick **Babylon Tours** if: - It’s your **first visit** - You want a **smooth, well-organized experience** - You care about **seeing highlights efficiently** - You want something reliably excellent ### 👉 Pick **Context Travel** if: - You love **history/art/architecture deeply** - You want a **small, discussion-based experience** - You don’t mind paying more - You prefer **depth over coverage** --- # 🧭 Simple Decision Rule - “I want the best tour” → **Babylon Tours** - “I want to *really understand* what I’m seeing” → **Context Travel** --- If you tell me *which city and sites you’re considering* (e.g., Vatican, Louvre, Colosseum), I can recommend which company is better **for that specific tour**—because the answer actually changes depending on the location. | E6: chatgpt/default | F6: US | G6: 1 | H6: Babylon Tours
A7: ch_b51b3b19-f211-5d2b-9dbf-4641ef095e7e | B7: chatgpt/default | C7: Babylon Tours vs Context Travel | D7: Ah, comparing **Babylon Tours** and **Context Travel**—two very different styles of travel experiences, though they sometimes overlap in target audience. Let’s break this down clearly so you can see which might suit your travel style. --- ### **1. Focus & Philosophy** **Babylon Tours** - Primarily focused on **private tours**, often in the Middle East and Mediterranean regions (e.g., Israel, Jordan, Turkey, Egypt). - Tours often combine **historical/cultural insight with logistical convenience**. - Can cater to **groups, families, or individual travelers**. - Sometimes more **generalist** in approach—less about ultra-specialized academic insight, more about accessible, rich historical storytelling. **Context Travel** - Geared toward **deep, scholarly exploration**. - Focus on **small groups** (often capped at ~8 people) and **experts as guides** (professors, art historians, archaeologists, chefs, etc.). - Tours are **theme-driven and academic**: e.g., “The Hidden History of Venice Canals” or “Archaeology of Ancient Jerusalem.” - Targets travelers who want **intellectual engagement**, not just sightseeing. --- ### **2. Tour Format & Style** **Babylon Tours** - Mix of **private tours and small groups**. - Flexible itineraries; often customizable to your schedule. - Guides are knowledgeable but may not always be academics. - Focus can include **sightseeing, cultural highlights, and photography**. **Context Travel** - Very structured around **in-depth learning**. - Small groups allow **direct interaction with the expert guide**. - Encourages **discussion, Q&A, and critical thinking**. - More **slow-paced**, meant for immersion rather than “see as much as possible.” --- ### **3. Price & Value** **Babylon Tours** - Often more affordable than Context Travel for private tours. - Prices vary depending on group size and customization. - Good balance of convenience + insight. **Context Travel** - Premium pricing—reflecting the **expert guides and intensive educational content**. - If your goal is deep intellectual engagement, the price is usually justified. --- ### **4. Best For** **Babylon Tours** - Travelers who want **flexible, private, or family-friendly tours**. - Those looking for a mix of **history, culture, and sightseeing** without requiring academic-level depth. **Context Travel** - Travelers who enjoy **learning from specialists**. - People who prefer **small, intimate groups** and **in-depth exploration** over seeing everything quickly. - Perfect for **history buffs, art lovers, or cultural scholars**. --- **Bottom line:** - **Babylon Tours** = convenient, insightful, flexible, and culturally rich. - **Context Travel** = intimate, scholarly, educational, and immersive. If you want, I can make a **quick table comparing specific tours in Jerusalem, Rome, or Istanbul**, showing exactly what each company offers and the cost differences. That can make the choice even clearer. Do you want me to do that? | E7: chatgpt/default | F7: US | G7: 1 | H7: Babylon Tours
A8: ch_95f9ee78-4d56-5f69-aa9d-1a06218728c9 | B8: chatgpt/default | C8: Babylon Tours vs Context Travel | D8: Here’s a clear, experience-based comparison of **Babylon Tours vs. Context Travel**—they target slightly different travelers even though both do small-group walking tours. --- # 🆚 Babylon Tours vs. Context Travel ## 🧠 1. Guide quality & depth **Context Travel** - Guides are typically **PhDs, historians, archaeologists, art experts** ​​​​​​​​​​​​​​​​​​​ - Focus is on **deep, intellectual understanding** (almost like a mini seminar) ​​​​​​​​​​​​​​​​​​​ - Strong storytelling + academic insight **Babylon Tours** - High-quality guides, but generally **not academic specialists** - More focused on **engaging, informative, but accessible tours** 👉 **Verdict:** - Want *serious depth / “learn a lot”* → Context - Want *great guide but lighter tone* → Babylon --- ## 👥 2. Group size & style **Context Travel** - Very small: usually **~6 people max** ​​​​​​​​​​​​​​​​​​​ - Highly interactive and customizable **Babylon Tours** - Also small groups, but typically **a bit larger (still intimate)** - More structured, less tailored 👉 **Verdict:** Context is more intimate and personalized. --- ## 💸 3. Price **Context Travel** - **Premium / expensive** - Often 30–50% higher than standard tours ​​​​​​​​​​​​​​​​​​​ **Babylon Tours** - **Mid-range pricing** - Generally cheaper than Context 👉 **Verdict:** - Budget-conscious → Babylon - Willing to pay for top-tier experience → Context --- ## 🎯 4. Experience style **Context Travel** - “**Depth over checklist**” philosophy ​​​​​​​​​​​​​​​​​​​ - Slower pace, discussion-heavy - Best for: - history buffs - art lovers - curious travelers **Babylon Tours** - More **classic guided tour feel** - Covers highlights efficiently - Best for: - first-time visitors - people who want structure + energy --- ## ⭐ 5. Reputation & consistency **Context Travel** - Very strong reputation for **quality + expertise** - Some variability depending on guide (rare but noted) **Babylon Tours** - **Highly rated on TripAdvisor** and widely used ​​​​​​​​​​​​​​​​​​​ - More consistent “tour company” experience --- ## 🧑​🤝​🧑 Real traveler sentiment (useful nuance) From Reddit: > “Context…small group…experts…pricey, but you get what you pay for.” ​​​​​​​​​​​​​​​​​​​ Also: > “Mixed reviews…some guides amazing, others not.” ​​​​​​​​​​​​​​​​​​​ 👉 Translation: Context is **high ceiling, but guide-dependent**. --- # 🧭 Bottom line **Choose Context Travel if:** - You want a **deep, intellectual experience** - You love history/art and asking questions - Budget is less of a concern **Choose Babylon Tours if:** - You want a **great, reliable tour at a better price** - You prefer a **lighter, more traditional guided experience** - It’s your first visit and you want highlights done well --- ✅ **Simple rule of thumb:** - *Context = “graduate-level cultural experience”* - *Babylon = “excellent premium sightseeing tour”* --- If you tell me the city (Rome, Paris, etc.) and what you care about (food, art, skip-the-line, etc.), I can recommend which one is actually better for your specific trip. | E8: chatgpt/default | F8: US | G8: 1 | H8: Babylon Tours
A9: ch_93f4e6bc-9eeb-497d-93ce-acfb3bce06cd | B9: chatgpt/default | C9: Babylon Tours vs Context Travel | D9: Here’s a direct comparison of **Babylon Tours vs. Context Travel** to help you decide which might suit your travel style better: ### **Babylon Tours** - Well​rated tour operator known for **private museum and walking tours** in major cities like Paris, London, NYC, Washington DC and more. They often rank *very highly* on places like TripAdvisor, with thousands of reviews and top rankings for experiences like Louvre tours. ​​​​​​​​​​​​​​​​​​​​​​​​​​​​​​​​​ - Focus is largely on **guided tours and museum experiences** — often private or small group, but **not specifically academic​expert led**. ​​​​​​​​​​​​​​​​​​​ - Tours can be **more mainstream in focus**, covering the key sights with knowledgeable local guides. ​​​​​​​​​​​​​​​​​​​ - Often gets praise for **high review scores and personable guides**, including local insight and engagement with art or history. ​​​​​​​​​​​​​​​​​​​​ ### **Context Travel** - Known for **deep, scholarly, expert​led tours**, often with guides who are **academics, historians, or subject​matter experts** rather than typical tour guides. ​​​​​​​​​​​​​​​​​​​​​​​​​​​​​​​​ - Emphasis is on **intellectual, themed experiences** — exploring history, art, architecture, culture in depth rather than just hitting the checkpoints. ​​​​​​​​​​​​​​​​​​​ - Tours are often **small group or private**, with a focus on tailored experiences and engagement rather than scripted tours. ​​​​​​​​​​​​​​​​​​​​ - Generally regarded as **higher on depth and educational value**, but sometimes **more expensive** and can receive mixed feedback on consistency. ​​​​​​​​​​​​​​​​​​​ ### **Key Differences** **Depth & Style** - *Babylon Tours* → solid guided tours with local expertise and strong guest reviews. ​​​​​​​​​​​​​​​​​​​ - *Context Travel* → deep, discussion​driven tours led by experts, ideal for travelers who want more context and meaning. ​​​​​​​​​​​​​​​​​​​ **Pricing & Experience** - Babylon tends to be more **mainstream and broadly reviewed**, whereas Context often costs more for its expert focus. ​​​​​​​​​​​​​​​​​​​ **Group Size** - Both offer small group or private options, but Context often *limits group size* intentionally to promote discussion. ​​​​​​​​​​​​​​​​​​​ **Best For** - **Babylon Tours** → travelers who want quality guided experiences with strong reviewer popularity. ​​​​​​​​​​​​​​​​​​​ - **Context Travel** → travelers seeking **in​depth cultural/historical understanding** from expert guides. ​​​​​​​​​​​​​​​​​​​​ If you want *show​and​tell tours with excellent guides*, Babylon is great — but if you want to *deeply understand a place through academic storytelling*, Context Travel is often worth the investment. ​​​​​​​​​​​​​​​​​​​ | E9: chatgpt/default | F9: US | G9: 1 | H9: Babylon Tours
A10: ch_83f21f33-7547-47cc-8335-28c3925efb89 | B10: chatgpt/default | C10: Babylon Tours vs Context Travel | D10: Babylon Tours and Context Travel are both popular tour companies, but they have different focuses, styles, and pricing structures. Here's a comparison to help you decide which one might suit your travel needs best: ### **Babylon Tours** **Focus & Style:** - **Private & Customized Tours:** Babylon Tours specializes in tailor-made, private tours. They focus on creating a personalized experience for each traveler or small group, which means they can adjust the itinerary according to your preferences. - **Luxury & VIP Experiences:** Babylon Tours often cater to those looking for a more high-end or VIP experience, offering luxury vehicles, expert guides, and access to exclusive sites. - **Destinations:** They offer tours in a variety of cities and countries around the world, with a particular emphasis on major European and Middle Eastern destinations. **Pros:** - Customizable itineraries. - Flexible schedules. - Focus on exclusive experiences and luxury. - Great for small groups or private tours. **Cons:** - Can be more expensive, especially for luxury options. - Less suited for those looking for budget-friendly tours. ### **Context Travel** **Focus & Style:** - **Intellectual & Immersive Tours:** Context Travel focuses on providing deeply informative, intellectually stimulating tours. Their tours are often led by experts, including historians, archaeologists, and professors, making them great for those who want a deeper dive into the history and culture of a location. - **Small Group Focus:** They specialize in small group tours (usually 6–8 people) which fosters a more intimate and discussion-based environment. - **Destinations:** Context Travel is more focused on cultural and historical experiences, with tours in cities across Europe, the U.S., and a few other international destinations. **Pros:** - In-depth, educational experiences. - Small group tours for a more personal atmosphere. - Expert-led tours, with a focus on cultural history and local knowledge. - Ideal for history buffs and those seeking educational travel. **Cons:** - Tours may be more academic or research-focused, so not ideal if you're looking for a light, touristy experience. - Typically more expensive than group tours, though more affordable than luxury private tours. ### **Key Differences:** - **Personalization:** Babylon Tours offers fully customizable, private tours, while Context Travel tends to focus on pre-designed, small-group tours with a heavy educational angle. - **Tour Type:** Babylon Tours provides a luxury experience with high-end options, whereas Context Travel is more about in-depth, intellectual exploration in a more intimate setting. - **Audience:** Babylon Tours is ideal for those seeking comfort, luxury, and privacy, while Context Travel is better suited for travelers who want to connect with experts and learn deeply about history, art, and culture in small groups. ### **Which One to Choose?** - **Babylon Tours**: Go for this if you value a more exclusive, flexible, and luxurious experience and are looking for a private, tailored tour. - **Context Travel**: Choose this if you're an intellectual traveler who wants to engage deeply with the history, art, and culture of a place in a small group setting. It really depends on what kind of travel experience you're after! | E10: chatgpt/default | F10: US | G10: 1 | H10: Babylon Tours
A11: ch_783cb01d-1ca5-413d-ac90-f4fb1544085c | B11: chatgpt/default | C11: Babylon Tours vs Context Travel | D11: Here’s a clear comparison between the two companies so you can see how **Babylon Tours​​​​​​​​​​​​​​​​​​​​​​​​​​​​​​​​​​​​​​​​​​​​​​** and **Context Travel​​​​​​​​​​​​​​​​​​​​​​​​​​​​​​​​​​​​​​​​​​​​​​** differ and which might suit your travel style better: --- ## 🗺️ **Overview & Focus** ### **Babylon Tours** - Specializes in **private and small-group museum and city walking tours** in major cities like Paris, London, New York, Washington​D.C., Rome, etc. ​​​​​​​​​​​​​​​​​​​ - Tours are known for being **highly rated on TripAdvisor** (often 5⭐ with thousands of reviews). ​​​​​​​​​​​​​​​​​​​​​​​​​​​​​​​​​ - Emphasis on bringing **art, culture, and city history to life** through engaging local guides. ​​​​​​​​​​​​​​​​​​​ - Often includes **museum entry & skip​the​line features** on flagship tours (e.g., Louvre). ​​​​​​​​​​​​​​​​​​​​ 👉 **Good fit** if you want: ✔ high​rated mainstream tours with local guides ✔ a balance of storytelling and sightseeing ✔ classic museum highlights or city basics --- ### **Context Travel** - Offers **deep, educational walking tours** in **60+ cities worldwide** focused on art, architecture, history, food, and culture. ​​​​​​​​​​​​​​​​​​​ - Guides are typically **scholars, historians, archaeologists, or subject​matter experts** (often with advanced degrees). ​​​​​​​​​​​​​​​​​​​​ - Tour formats include **small group (usually ≤6–10 people)**, private tours, audio guides, and pre​trip lectures. ​​​​​​​​​​​​​​​​​​​ - Tours are **interactive conversations**, not scripted monologues, and often tailor content to interests. ​​​​​​​​​​​​​​​​​​​ 👉 **Good fit** if you want: ✔ a **deep, intellectual experience** with expert insight ✔ small, discussion​oriented groups ✔ contextual storytelling beyond the surface level --- ## 👥 **Guide Style & Expertise** | Feature | Babylon Tours | Context Travel | |---------|---------------|-----------------| | Guide Background | Local professional guides (solid knowledge) | Often experts/scholars (archaeologists, historians) | | Depth of Content | Educational and engaging but broad | In depth, tailored, analytical | | Group Size | Private or small groups | Very small groups (intimate) | **Summary:** Context’s guides lean more toward academic expertise, while Babylon’s are excellent general interpreters of local culture and history. --- ## 💬 **What Travelers Say** ### Babylon Tours ✔ Very high TripAdvisor ratings (multiple cities) ​​​​​​​​​​​​​​​​​​​ ✔ Guides described as personable, engaging, adaptable ​​​​​​​​​​​​​​​​​​​​ 👎 Some external review aggregators show mixed sentiment (but TripAdvisor ratings are strong) ​​​​​​​​​​​​​​​​​​​​ ### Context Travel ✔ Excellent reviews emphasizing **conversation​style tours** and knowledgeable leaders ​​​​​​​​​​​​​​​​​​​ ✔ Many travelers describe tours as **transformative and tailored** ​​​​​​​​​​​​​​​​​​​ 👎 A few note **higher price points** and occasional mismatch between guide style and expectations (general volume tours) ​​​​​​​​​​​​​​​​​​​ --- ## 💰 **Pricing & Value** - **Context Travel** tends to be **more expensive** due to smaller groups and expert-level guides. ​​​​​​​​​​​​​​​​​​​​ - **Babylon Tours** often offers competitive pricing with strong value for mainstream museum and city walk experiences. ​​​​​​​​​​​​​​​​​​​ --- ## 🧭 **Who Should Choose Which?** **Choose *Babylon Tours*** if you want: ✅ Highly rated tours with engaging local guides ✅ Classic highlights and museum tours ✅ Good balance of cost and quality **Choose *Context Travel*** if you want: 🎓 Deep, analytical insights into art, history, and culture 🗣️ Personalized, discussion​oriented experiences 🌍 Small group formats and expert guides --- ## 🧠 **Bottom Line** - **Context Travel** is ideal for curious travelers who want to *understand* a destination on a deeper level, often with academic insight and tailored dialogue. - **Babylon Tours** is excellent for travelers wanting highly rated, **expert​led but broadly engaging experiences**, especially in museums and city centers. --- If you tell me **what kind of trip you’re planning** (city, interests, budget), I can recommend which one might suit your itinerary best! | E11: chatgpt/default | F11: US | G11: 1 | H11: Babylon Tours
A12: ch_d7130957-65d1-5e1f-8b0a-26a5e0fc7f6e | B12: chatgpt/default | C12: Recommended Paris museum tours | D12: Paris has some of the best museum tours in the world—but the “right” one depends on whether you want a highlights overview, deep art history, or a more relaxed/private experience. Here are **top recommended Paris museum tours (with clear picks by style):** --- # 🎨 Best Paris Museum Tours ## 1. Classic “Must-See” Combo Tour (Best for first-time visitors) - **Louvre Museum​​​​​​​​​​​​​​​​​​​​​​​​​​​​​​​​​​​​​​​​​​​​​​​​ + Musée d'Orsay​​​​​​​​​​​​​​​​​​​​​​​​​​​​​​​​​​​​​​​​​​​​​​​​ guided combo** - ⏱ ~3–5.5 hours - 💡 Includes skip-the-line access + expert guide 👉 Why it’s great: - Covers **Paris’s two most important museums in one day** - You’ll see highlights like the *Mona Lisa* and Impressionist masterpieces - Guides help you navigate huge collections efficiently 📌 Example: Reserved-access Louvre tour + Orsay ticket (~€123) ​​​​​​​​​​​​​​​​​​​ 📌 Some tours offer small groups (6–8 people) for a more personal experience ​​​​​​​​​​​​​​​​​​​ --- ## 2. Louvre Highlights Guided Tour (Best overall single museum tour) - **Louvre Museum​​​​​​​​​​​​​​​​​​​​​​​​​​​​​​​​​​​​​​​​​​​​​​​​ skip-the-line guided tour** - ⏱ 1.5–2.5 hours 👉 Why it’s great: - The Louvre is विशाल—**guided tours prevent overwhelm** - Focus on key works: *Venus de Milo*, *Winged Victory*, *Mona Lisa* - Often includes priority entry 📌 Typical tours start around €79–€95 and last ~2 hours ​​​​​​​​​​​​​​​​​​​ 💬 Traveler insight (Reddit): > “You skip lines and it’s very informative—highly recommend.” ​​​​​​​​​​​​​​​​​​​​ --- ## 3. Musée d’Orsay Impressionist Tour (Best for art lovers) - **Musée d'Orsay​​​​​​​​​​​​​​​​​​​​​​​​​​​​​​​​​​​​​​​​​​​​​​​​ guided tour** - ⏱ ~2 hours 👉 Why it’s great: - Focused on **Impressionism (Monet, Van Gogh, Degas)** - Easier to digest than the Louvre - Beautiful setting (former train station) 📌 Private or small-group tours often include skip-the-line access ​​​​​​​​​​​​​​​​​​​ --- ## 4. Private Museum Tours (Best for flexibility & depth) - Available at: - **Louvre Museum​​​​​​​​​​​​​​​​​​​​​​​​​​​​​​​​​​​​​​​​​​​​​​​​** - **Musée Picasso​​​​​​​​​​​​​​​​​​​​​​​​​​​​​​​​​​​​​​​​​​​​​​​​** - **Centre Pompidou​​​​​​​​​​​​​​​​​​​​​​​​​​​​​​​​​​​​​​​​​​​​​​​​** 👉 Why it’s great: - Fully customized pacing and focus - Great if you want: - deeper art history - fewer crowds - kid-friendly or themed tours 📌 Many companies offer private guides for major museums ​​​​​​​​​​​​​​​​​​​ --- ## 5. Family / Kid-Friendly Louvre Tours - Treasure hunt–style tours at the **Louvre Museum​​​​​​​​​​​​​​​​​​​​​​​​​​​​​​​​​​​​​​​​​​​​​​​​** 👉 Why it’s great: - Keeps kids engaged - Interactive storytelling format 📌 Designed specifically for families with shorter attention spans ​​​​​​​​​​​​​​​​​​​ --- ## 6. Niche / Alternative Museum Tours Great if you’ve already done the big ones: - **Musée de l'Orangerie​​​​​​​​​​​​​​​​​​​​​​​​​​​​​​​​​​​​​​​​​​​​​​​​** → Monet’s Water Lilies (short visit) - **Musée Rodin​​​​​​​​​​​​​​​​​​​​​​​​​​​​​​​​​​​​​​​​​​​​​​​​** → sculpture + garden - **Centre Pompidou​​​​​​​​​​​​​​​​​​​​​​​​​​​​​​​​​​​​​​​​​​​​​​​​** → modern/contemporary art 👉 Tip: Smaller museums often don’t *require* a guide—some travelers prefer self-paced visits. --- # 🧭 How to Choose the Right Tour - **First time in Paris?** → Combo (Louvre + Orsay) - **Short on time?** → Louvre highlights tour - **Love Impressionism?** → Orsay guided tour - **Want depth / fewer crowds?** → Private tour - **Traveling with kids?** → Family-focused Louvre tour --- # ⚠️ Practical Tips - Book in advance—tours sell out quickly - Guided tours often include tickets (important!) - Expect security lines even with “skip-the-line” - Louvre alone can take **3+ hours without a guide** --- If you want, tell me: - your trip length - interests (casual vs serious art) - budget …and I can suggest a **personalized Paris museum itinerary + exact tours to book**. | E12: chatgpt/default | F12: US | G12: -
A13: ch_d4a1f113-8da4-585c-a6fa-debcaa9ccbbd | B13: chatgpt/default | C13: Recommended Paris museum tours | D13: Paris has some of the best museum tours in the world—but the “right” one depends on your style (fast highlights vs deep dive, private vs group, art lover vs casual visitor). Here are **top recommended museum tours in Paris**, organized by type so you can quickly pick what fits you. --- # 🎨 Best Paris Museum Tours ## 🏛️ 1. Louvre Highlights Guided Tour (Best for first-time visitors) At the Louvre Museum​​​​​​​​​​​​​​​​​​​​​​​​​​​​​​​​​​​​​​​​​​​​​​​​​ - ⏱️ ~2–3 hours - ⭐ Focus: Mona Lisa, Venus de Milo, Winged Victory - 👍 Skip-the-line entry + expert storytelling 👉 Why it’s worth it: The Louvre is विशाल (35,000+ works), so a guide helps you **avoid getting overwhelmed and see the essentials efficiently**. ​​​​​​​​​​​​​​​​​​​ 💡 Popular options: - “Secrets of the Louvre” or “Mona Lisa highlights” tours (~2.5 hrs) ​​​​​​​​​​​​​​​​​​​ - Small-group or semi-private versions for a more personal feel 👉 Best for: First-time visitors or short stays --- ## 🖼️ 2. Musée d’Orsay Impressionist Tour (Best for art lovers) At the Musée d'Orsay​​​​​​​​​​​​​​​​​​​​​​​​​​​​​​​​​​​​​​​​​​​​​​​​​ - ⏱️ ~2 hours - 🎨 Focus: Monet, Van Gogh, Degas - 👍 Skip-the-line + expert in Impressionism 👉 Why it’s special: Orsay is more manageable and **tells a clear story of art evolution (1848–1914)** ​​​​​​​​​​​​​​​​​​​ 💡 Many tours include: - Deep context on Impressionism - Time after the tour to explore on your own ​​​​​​​​​​​​​​​​​​​ 👉 Best for: People who actually want to understand art (not just see famous pieces) --- ## 🧑​🎨 3. Louvre + Orsay Combo Tour (Best overall value) Covers both Louvre Museum​​​​​​​​​​​​​​​​​​​​​​​​​​​​​​​​​​​​​​​​​​​​​​​​​ + Musée d'Orsay​​​​​​​​​​​​​​​​​​​​​​​​​​​​​​​​​​​​​​​​​​​​​​​​​ - ⏱️ ~3–5 hours (sometimes split across days) - 💸 Typically better value than booking separately - 👍 Seamless tickets + guided Louvre + Orsay access 👉 Why choose it: - Covers **ancient → modern art in one plan** - Saves time with pre-arranged entry ​​​​​​​​​​​​​​​​​​​ 👉 Best for: Short trips or “see-it-all” travelers --- ## 👨​👩​👧​👦 4. Private or Family-Friendly Museum Tours Available at Louvre, Orsay, and others - 🧑​🏫 Private guide = fully customizable - 🎯 Options like: - Kids treasure hunts (Louvre) - Deep-dive art history tours - 👍 More engaging, flexible pacing 👉 Why it’s worth it: Private tours **adapt to your interests and attention span**, which is huge in massive museums ​​​​​​​​​​​​​​​​​​​ 👉 Best for: Families, couples, or serious art fans --- ## 🌃 5. After-Hours / Evening Louvre Tours (Most unique experience) At the Louvre Museum​​​​​​​​​​​​​​​​​​​​​​​​​​​​​​​​​​​​​​​​​​​​​​​​​ - 🌙 Smaller crowds - 🎧 More intimate atmosphere - 📸 Better viewing of major works 👉 Why people love it: You get a **calmer, less chaotic Louvre experience**, especially around the Mona Lisa ​​​​​​​​​​​​​​​​​​​ 👉 Best for: Avoiding crowds + unique vibe --- # 🧭 Quick Comparison | Tour Type | Best For | Time | Experience Level | |----------|---------|------|------------------| | Louvre Highlights | First-timers | 2–3 hrs | Efficient overview | | Orsay Impressionist | Art lovers | ~2 hrs | Deeper understanding | | Combo Tour | Short trips | 3–5 hrs | Broad coverage | | Private Tour | Families / enthusiasts | Flexible | Customized | | Evening Louvre | Unique experience | 2–3 hrs | Less crowded | --- # 💡 Practical Tips (from real traveler feedback + experts) - Guided tours often **skip long lines and save hours** - The Louvre is so big that going solo = you’ll miss key works - Some travelers say guided tours are “absolutely worth it” for context and efficiency - Note: Some tours now include their own tickets (museum passes may not apply) ​​​​​​​​​​​​​​​​​​​​ --- # 👍 My recommendation If you want a simple answer: - **1 museum only →** Louvre Highlights tour - **2 museums →** Combo (Louvre + Orsay) - **Art-focused trip →** Orsay + private guide - **Hate crowds →** Evening Louvre tour --- If you tell me your travel style (budget, group size, how many days in Paris), I can suggest **specific tours with exact booking links** tailored to you. | E13: chatgpt/default | F13: US | G13: -
A14: ch_a982414e-eadf-596a-90d1-aa62e21b07bf | B14: chatgpt/default | C14: Recommended Paris museum tours | D14: Here are some of the **best Paris museum tours**—whether you want a classic Louvre experience, Impressionist deep dive, or a combo tour to maximize your time. --- # 🎨 Top Recommended Paris Museum Tours ## 🏛️ 1. Louvre Museum​​​​​​​​​​​​​​​​​​​​​​​​​​​​​​​​​​​​​​​​​​​​​​​​​ skip-the-line guided tours **Best for:** First-time visitors, highlights, avoiding overwhelm - **Louvre Masterpieces Tour (2–3 hours)** - Covers icons like the *Mona Lisa* and *Venus de Milo* - Includes **skip-the-line entry + expert guide** - Great for getting oriented in a massive museum ​​​​​​​​​​​​​​​​​​​ - **Small-group or semi-private tours** - More interaction with the guide - Often capped at 6–10 people for a richer experience ​​​​​​​​​​​​​​​​​​​ - **Evening / “Mona Lisa without crowds” tours** - Visit at quieter hours - Ideal if you want fewer crowds and better viewing ​​​​​​​​​​​​​​​​​​​ 👉 Why it’s worth it: The Louvre is विशाल—guided tours help you see the essentials efficiently and skip long lines. --- ## 🖼️ 2. Musée d’Orsay​​​​​​​​​​​​​​​​​​​​​​​​​​​​​​​​​​​​​​​​​​​​​​​​​ Impressionist tours **Best for:** Art lovers, Monet/Van Gogh fans - **Impressionist highlights tour (2–2.5 hours)** - Focus on Monet, Renoir, Degas, Van Gogh - Led by art-history specialists - Skip-the-line entry included ​​​​​​​​​​​​​​​​​​​ - **Semi-private Orsay tours** - Small groups (often under 8 people) - More storytelling + deeper context ​​​​​​​​​​​​​​​​​​​​ 👉 Why it’s worth it: The Orsay is more manageable than the Louvre, but a guide really enhances the stories behind Impressionism. --- ## 🧠 3. Louvre + Orsay combo tours **Best for:** Short stays, efficiency - **Half-day combo (5–6 hours)** - Guided visit of both museums - Skip-the-line access at each - Small groups available ​​​​​​​​​​​​​​​​​​​ - **Louvre guided + Orsay ticket combo** - Guided Louvre visit + flexible Orsay entry later ​​​​​​​​​​​​​​​​​​​ 👉 Why it’s worth it: Covers Paris’s two most important museums in one streamlined experience. --- ## 🎭 4. Specialty & niche museum tours **Best for:** Repeat visitors or specific interests - **Centre Pompidou​​​​​​​​​​​​​​​​​​​​​​​​​​​​​​​​​​​​​​​​​​​​​​​​​ modern art tours** - Picasso, Warhol, contemporary works ​​​​​​​​​​​​​​​​​​​ - **Musée Picasso​​​​​​​​​​​​​​​​​​​​​​​​​​​​​​​​​​​​​​​​​​​​​​​​​ guided tours** - Deep dive into Picasso’s life and evolution - **Family / kids tours (especially Louvre)** - Treasure hunts, interactive storytelling ​​​​​​​​​​​​​​​​​​​ 👉 Why it’s worth it: Great if you’ve already seen the big two or want a more unique angle. --- ## 💡 How to choose the right tour - **Short trip (1–3 days):** Combo Louvre + Orsay - **First time in Paris:** Louvre highlights + Orsay Impressionist - **Art enthusiast:** Small-group or private tours - **Traveling with kids:** Interactive Louvre tour 👉 Pro tip: Paris museums are extremely busy (millions of visitors yearly), so **skip-the-line guided tours save hours and add context** ​​​​​​​​​​​​​​​​​​​ --- If you want, tell me: - your travel dates - budget - private vs small group …and I can suggest **specific bookable tours (with pricing & best providers)** tailored to you. | E14: chatgpt/default | F14: US | G14: -
A15: ch_fd42ef14-c01d-5205-89fa-528c688c616b | B15: chatgpt/default | C15: Recommended Paris museum tours | D15: ​​​​​ Here are some **recommended museum tours and tour providers in Paris** — perfect for exploring world​famous collections like the *Louvre*, *Musée d’Orsay*, and more with expert insight and often skip​the​line access: ​​​​​​​​​​​​​​​​​​​​​​​​​​​​​​​​ ### 🎨 Top Paris Museum Tour Options #### 🖼️ Louvre & Major Art Tours - **Louvre Museum Masterpieces Guided Tour** – Small​group walk through the Louvre’s highlights including the *Mona Lisa* and Venus de Milo with expert commentary and skip the entry queues. ​​​​​​​​​​​​​​​​​​​​ - **VIP Louvre Tours** – 2​hour VIP or semi​private options that dive deeper into the world’s largest art museum with curated commentary. ​​​​​​​​​​​​​​​​​​​ #### 🎨 Impressionist & Other Art Museum Tours - **Musée d’Orsay Guided Tour** – Focused visit through Impressionist and post​Impressionist treasures like Monet and Van Gogh. ​​​​​​​​​​​​​​​​​​​​ - **Orangerie & Other Museum Tickets** – Combo or skip​line options are available for other notable art spaces. ​​​​​​​​​​​​​​​​​​​ #### 🧑​🎨 Specialized & Private Museum Experiences - **Paris Muse | Private & Family Tours​​​​​​​​​​​​​​​​​​​​​​​​​​​​​​​​** – Highly rated private museum tours with art​history instructor guides, including family​friendly options. - **Explore Paris Tours​​​​​​​​​​​​​​​​​​​​​​​​​​​​​​​​** – Local tour agency offering custom and group museum tours (often including Louvre and beyond). - **Babylon Tours Paris​​​​​​​​​​​​​​​​​​​​​​​​​​​​​​​​** – Extremely highly reviewed Paris sightseeing and museum tour operator. - **White Umbrella Tours Paris​​​​​​​​​​​​​​​​​​​​​​​​​​​​​​​​​** – Well​rated guided tours of Paris highlights including museum visits and cultural context tours. ### 🗺️ Other Recommended Tour Providers - **Meet The Locals - Paris, London & Rome Family Tours​​​​​​​​​​​​​​​​​​​​​​​​​​​​​​​​** – Great choice for personalized, engaging tours near the city’s art hubs. - **Memories France - Paris Tours​​​​​​​​​​​​​​​​​​​​​​​​​​​​​​​​​** – Stylish small​group cultural and museum tour experiences. - **Tour Guides France - Official Tour Guides in France​​​​​​​​​​​​​​​​​​​​​​​​​​​​​​​​** – Local experts with flexible museum and historical tours. - **Christopher's Paris Guided Tours​​​​​​​​​​​​​​​​​​​​​​​​​​​​​​​​** – Small​group guided touring with cultural and museum focus. ### 🖼️ Key Museums Often Included - **Louvre Museum​​​​​​​​​​​​​​​​​​​​​​​​​​​​​​​​** – The world’s largest art museum, essential for guided tours. - **Musée d'Orsay​​​​​​​​​​​​​​​​​​​​​​​​​​​​​​​​​** – Iconic for Impressionist masters and a popular guided tour pick. - **Musée Rodin​​​​​​​​​​​​​​​​​​​​​​​​​​​​​​​​​** – Great for sculpture and a more intimate art​tour experience. ​​​​​​​​​​​​​​​​​​​ --- ### 📌 Tips for Booking - **Skip​the​line access and skip entry waits** is a major perk of guided museum tours in Paris — especially at the Louvre. ​​​​​​​​​​​​​​​​​​​​ - **Small​group or private tours** generally offer deeper insights and more personalization than large group tours. ​​​​​​​​​​​​​​​​​​​ - Combining museums like the Louvre, Orsay, and smaller houses (e.g., Rodin or Orangerie) into a single day tour can give a more comprehensive art experience. ​​​​​​​​​​​​​​​​​​​ Would you like **specific recommendations based on how much time you have in Paris** (half​day vs. full​day tours)? | E15: chatgpt/default | F15: US | G15: 1 | H15: Babylon Tours
A16: ch_d928181e-f507-4a32-a01c-483ff84862e5 | B16: chatgpt/default | C16: Recommended Paris museum tours | D16: Paris is a treasure trove of art, culture, and history, with museums that cater to almost every interest! If you’re looking for recommended museum tours, here are some of the best ones, each offering a unique experience: ### 1. **Louvre Museum Tour** - **What to Expect:** The Louvre is one of the largest and most famous museums in the world. It’s home to iconic works like the *Mona Lisa* and *Venus de Milo*. - **Tour Highlights:** Skip-the-line tours often include the must-see works, plus a guide to help you navigate the expansive galleries. You can also focus on specific collections, like the Egyptian antiquities or Renaissance art. - **Ideal for:** Art lovers, history buffs, and first-time visitors to Paris. ### 2. **Musée d’Orsay Tour** - **What to Expect:** Housed in a former railway station, this museum focuses on art from the 19th and early 20th centuries, including works by Monet, Van Gogh, Degas, and more. - **Tour Highlights:** An in-depth exploration of Impressionist and Post-Impressionist masterpieces, plus a chance to enjoy the museum's architecture. - **Ideal for:** Fans of Impressionism and early modern art. ### 3. **Musée de l'Orangerie Tour** - **What to Expect:** A smaller but spectacular museum known for its unique collection of Monet's *Water Lilies* and other works by artists like Cézanne and Picasso. - **Tour Highlights:** The immersive experience with Monet’s large *Water Lilies* murals is the highlight, along with exploring the museum's focus on early 20th-century art. - **Ideal for:** Those who want a quieter, more intimate museum experience. ### 4. **Centre Pompidou Tour** - **What to Expect:** A contemporary art hub known for its striking architecture and its collection of modern art. The museum houses works by artists like Kandinsky, Duchamp, and Matisse. - **Tour Highlights:** Explore avant-garde and experimental art, and don't miss the panoramic views of Paris from the rooftop. - **Ideal for:** Contemporary art enthusiasts and architecture lovers. ### 5. **Musée Rodin Tour** - **What to Expect:** Dedicated to the works of sculptor Auguste Rodin, this museum includes famous pieces like *The Thinker* and *The Gates of Hell*. The museum is set in a beautiful garden. - **Tour Highlights:** A guided walk through Rodin’s masterpieces in both the museum and garden, providing insight into his process and philosophy. - **Ideal for:** Sculpture enthusiasts and those who enjoy outdoor museum experiences. ### 6. **Musée Jacquemart-André Tour** - **What to Expect:** A private mansion turned museum, offering an incredible collection of art, furniture, and décor from the 18th century, including works by Rembrandt, Fragonard, and more. - **Tour Highlights:** A more intimate experience with art collections in a historic Parisian mansion setting. - **Ideal for:** Lovers of history, art, and elegant French interiors. ### 7. **Musée Picasso Tour** - **What to Expect:** This museum focuses on the life and work of Pablo Picasso, with a huge collection of his paintings, sculptures, ceramics, and sketches. - **Tour Highlights:** The museum’s exhibitions focus on different phases of Picasso’s career, allowing visitors to dive deep into his evolving style and influences. - **Ideal for:** Picasso fans and those interested in 20th-century art. ### 8. **Musée des Arts Décoratifs Tour** - **What to Expect:** Situated in the Louvre’s western wing, this museum explores decorative arts, from period furniture to contemporary design and fashion. - **Tour Highlights:** The fashion and textile collections are a must-see, with changing exhibitions featuring designers and design history. - **Ideal for:** Design and fashion enthusiasts. ### 9. **Musée Cluny - National Museum of the Middle Ages Tour** - **What to Expect:** This museum offers a deep dive into the medieval period, showcasing tapestries, sculptures, and artifacts from the Middle Ages. - **Tour Highlights:** Don't miss the *Lady and the Unicorn* tapestries—one of the most significant medieval art collections. - **Ideal for:** History and medieval art lovers. ### 10. **Paris Walking Art Tours** - **What to Expect:** These tours typically combine visits to several museums and art galleries in a more interactive and personalized way, often led by a knowledgeable guide who focuses on a specific art movement, such as Impressionism or Surrealism. - **Tour Highlights:** Customizable itineraries that allow you to explore the city’s art scene more deeply, connecting historical context with specific pieces. - **Ideal for:** Art history buffs and those who want a tailored experience. --- Would you like more details about any of these tours or tips on how to book them? Or maybe you’re curious about something specific like group vs. private tours? Let me know! | E16: chatgpt/default | F16: US | G16: -
A17: ch_747d83e8-46fa-42e8-b486-1d575109f274 | B17: chatgpt/default | C17: Recommended Paris museum tours | D17: ​​​​​ Here are some well​reviewed **museum and art tour options in Paris** to help you plan your visit — from classic guided visits of major museums to knowledgeable local tour companies: ​​​​​​​​​​​​​​​​​​​​​​​​​​​​​​​​ ### 🖼️ Recommended Guided Museum Tours - **Louvre Museum tours** – guided visits with *skip​the​line* access and expert commentary, including highlights like the *Mona Lisa* and *Venus de Milo*. Options include multi​hour group or semi​private tours. ​​​​​​​​​​​​​​​​​​​ - In​depth or themed tours (e.g., *closing​time* Louvre sessions or specialist art history tours) are popular with art lovers. ​​​​​​​​​​​​​​​​​​​ ### 👨​🎨 Trusted Local Tour Operators in Paris These companies offer guided museum tours as well as cultural walking tours that can include art and museum highlights: **Top Rated Tour Agencies** - **Babylon Tours Paris​​​​​​​​​​​​​​​​​​​​​​​​​​​​​​​​** – very high reviews, offers small​group city and museum tours including art and history. - **Explore Paris Tours​​​​​​​​​​​​​​​​​​​​​​​​​​​​​​​​** – guided tours around landmarks and museums. - **Paris Muse | Private & Family Tours​​​​​​​​​​​​​​​​​​​​​​​​​​​​​​​​** – private or family​friendly tours tailored to interests like art and history. - **ExperienceFirst - Paris Tours​​​​​​​​​​​​​​​​​​​​​​​​​​​​​​​​​** – large selection of guided tours; many include museum highlights and skip​the​line options. - **White Umbrella Tours Paris​​​​​​​​​​​​​​​​​​​​​​​​​​​​​​​​​** – popular local guide company with cultural walks and museum visits. - **Meet The Locals - Paris Tours​​​​​​​​​​​​​​​​​​​​​​​​​​​​​​​​** – friendly small​group tours focused on local insights. - **Memories France - Paris Tours​​​​​​​​​​​​​​​​​​​​​​​​​​​​​​​​​** – well​reviewed for personalized experiences. - **Christopher's Paris Guided Tours​​​​​​​​​​​​​​​​​​​​​​​​​​​​​​​​** – smaller boutique operator with guide​led experiences. ### 🖼️ Museum Highlights to Include While doing tours, you might plan visits to Paris’s best​known museums such as **Louvre Museum​​​​​​​​​​​​​​​​​​​​​​​​​​​​​​​​** and **Musée d'Orsay​​​​​​​​​​​​​​​​​​​​​​​​​​​​​​​​​**, or choose specialized experiences focusing on Impressionist art, French history, or combined neighborhood walking + museum visits. ​​​​​​​​​​​​​​​​​​​ --- 💡 **Tips:** - Booking skip​the​line or semi​private tours in advance helps avoid long queues for major museums. ​​​​​​​​​​​​​​​​​​​ - Many guides also offer custom or theme​based tours (e.g., Renaissance art, French women artists, architecture). ​​​​​​​​​​​​​​​​​​​ Would you like a few specific tour suggestions by price or duration (e.g., short half​day vs full​day)? | E17: chatgpt/default | F17: US | G17: 1 | H17: Babylon Tours
A18: ch_56ba443c-2101-4164-9c5d-074453df0beb | B18: chatgpt/default | C18: Recommended Paris museum tours | D18: Here are some of the **best Paris museum tours** (especially for first-time visitors and art lovers), with options ranging from quick highlights to in-depth experiences. --- # 🎨 Top Recommended Paris Museum Tours ## 1. Louvre Museum (must-do) **Best overall museum tour in Paris** - **Skip-the-line guided tours (2–3 hours)** - See highlights like the Mona Lisa, Venus de Milo, Winged Victory - Expert guides help you navigate the massive museum efficiently - Often includes priority entrance via a dedicated group line ​​​​​​​​​​​​​​​​​​​ - **Small-group or VIP tours (6–10 people)** - More personalized and less rushed - Ideal if you want deeper storytelling and Q&A - **Closing-time or early-access tours** - Fewer crowds, better viewing experience 👉 Why it’s worth it: The Louvre is विशाल (over 35,000 works on display), and guided tours help you **avoid getting overwhelmed and save hours** ​​​​​​​​​​​​​​​​​​​ 💡 Tip: After the tour, you can usually stay and explore on your own. --- ## 2. Musée d’Orsay (Impressionist art lovers) **Best for Monet, Van Gogh, Degas** - **Impressionist highlights tours (1.5–2 hours)** - Focus on the most famous works - Learn the story behind Impressionism - **Art history deep dives** - Smaller groups with expert guides 👉 Why go: Often rated one of the **most enjoyable museum tours in Paris** thanks to its manageable size and iconic works ​​​​​​​​​​​​​​​​​​​ --- ## 3. Combo Tours (Great value) **Best if you want multiple highlights in one day** - Louvre + Eiffel Tower + Notre Dame walking tour - Louvre + Seine River cruise bundle - Museum + city highlights bike tours 👉 Good for short trips where you want to maximize time efficiently. --- ## 4. Private & Semi-Private Tours **Best for a premium experience** - Private Louvre or Orsay guide - Fully customizable itinerary - Skip-the-line access + tailored pacing 👉 Ideal for: - Families - Couples - Serious art enthusiasts --- ## 5. Themed & Alternative Museum Tours **Best for something unique** - **“Secrets of the Louvre” tours** - Hidden details, symbolism, lesser-known works - **Photography tours inside museums** - **Art + history storytelling tours** 👉 These make the experience more engaging than standard highlight tours. --- # 🪪 Paris Museum Pass (optional add-on) - Covers entry to **60+ museums and monuments** - Doesn’t always include guided tours - Best if you plan to visit multiple sites quickly ​​​​​​​​​​​​​​​​​​​ --- # 👍 What travelers say (from Reddit insights) - Guided tours are often described as **“worth it” and far more informative** - You don’t skip *all* lines (security still applies), but tours usually use **faster group entrances** - Many people say the guide helps them **see more in less time and actually understand the art** --- # 🧭 How to choose the right tour - **First time in Paris:** → Louvre skip-the-line highlights tour - **Art lover:** → Small-group or private tour - **Short trip (1–2 days):** → Combo tour - **Budget traveler:** → Timed-entry ticket + audio guide --- # 💡 Pro tips - Book at least **a few days in advance** (Louvre sells out often) - Go early morning or late afternoon to avoid peak crowds - Wear comfortable shoes — museums are huge - Don’t try to see everything (you can’t!) --- If you tell me your **budget, travel style, or how many days you have in Paris**, I can suggest specific tours that fit you perfectly. | E18: chatgpt/default | F18: US | G18: -
A19: ch_8e341d5f-560e-5572-ba03-85bf149efeca | B19: chatgpt/default | C19: Best Paris museum tours | D19: Paris is full of incredible museums, each offering a unique experience depending on your interests. Here are some of the best tours to check out, whether you're an art lover, history buff, or just looking to explore some hidden gems. ### 1. **Louvre Museum Tour** - **Highlights:** The Louvre is the world’s largest art museum and home to some of the most iconic works, like the **Mona Lisa**, **Venus de Milo**, and **Winged Victory of Samothrace**. - **Tour Tips:** Consider a **guided tour** to skip the lines and focus on the museum’s key masterpieces. Some tours are themed, focusing on ancient civilizations, the Renaissance, or even the museum's architecture. - **Duration:** 2–3 hours. ### 2. **Musée d'Orsay Tour** - **Highlights:** Known for its collection of Impressionist and Post-Impressionist masterpieces by **Monet**, **Van Gogh**, **Degas**, and **Renoir**, this museum is housed in a former railway station. - **Tour Tips:** A **guided tour** can help you understand the evolution of art from the 19th century to early 20th century. Don't miss the giant clock windows with views of the Seine. - **Duration:** 1.5–2 hours. ### 3. **Centre Pompidou Tour** - **Highlights:** This museum is dedicated to modern art, featuring works by **Picasso**, **Delaunay**, and **Kandinsky**. The building itself is an architectural marvel. - **Tour Tips:** Choose a **modern art tour** that covers both the exhibits and the history of the Centre Pompidou. You can also explore the **Beaubourg district** nearby. - **Duration:** 1.5–2 hours. ### 4. **Musée Rodin Tour** - **Highlights:** Home to **Rodin's** most famous sculptures like *The Thinker* and *The Kiss*. The beautiful gardens also add a tranquil element to the experience. - **Tour Tips:** Opt for a **garden and sculpture tour** to explore both the outdoor and indoor collections. The museum's intimate setting makes it a more relaxed experience compared to larger museums. - **Duration:** 1–1.5 hours. ### 5. **Musée de l'Orangerie Tour** - **Highlights:** Famous for its collection of **Monet’s Water Lilies** murals, as well as works by **Cézanne**, **Matisse**, and **Renoir**. - **Tour Tips:** Since it's a smaller museum, a **self-guided audio tour** is a great option for a deeper understanding of the Impressionist and Post-Impressionist pieces. - **Duration:** 1 hour. ### 6. **Palais Garnier (Opéra House) Tour** - **Highlights:** Not a traditional museum, but the **Palais Garnier** offers a fascinating glimpse into the world of opera and theater, and you can learn about its ornate architecture, as well as **Chagall's** ceiling. - **Tour Tips:** If you're into history and architecture, go for a **guided tour** that covers the building’s stories and hidden spots (including the famous **Phantom of the Opera** legend). - **Duration:** 1 hour. ### 7. **Musée Picasso Paris Tour** - **Highlights:** A deep dive into the life and work of **Pablo Picasso**, featuring over 5,000 works of art, sketches, and personal items. - **Tour Tips:** Choose a **Picasso-focused tour** to fully understand the evolution of his creative mind, from his blue period to cubism. - **Duration:** 1.5 hours. ### 8. **Conciergerie & Sainte-Chapelle Tour** - **Highlights:** These two sites provide a historical perspective on the French Revolution, with the **Conciergerie** being a former prison where **Marie Antoinette** was held, and **Sainte-Chapelle** offering stunning stained-glass windows. - **Tour Tips:** A **historical walking tour** can help connect the dots between the events of the Revolution and these historical landmarks. - **Duration:** 2 hours. ### 9. **Musée Jacquemart-André Tour** - **Highlights:** A lesser-known gem, this museum is housed in a former private mansion and features art from the **Renaissance** to the **18th century**. - **Tour Tips:** For a more intimate experience, take a **private guided tour** of the museum, which often isn’t as crowded as the larger institutions. - **Duration:** 1.5 hours. ### 10. **Musée Carnavalet (History of Paris)** - **Highlights:** This museum covers the history of Paris from the **French Revolution** to modern times. It’s housed in two beautiful historical mansions in Le Marais. - **Tour Tips:** Take a **historical tour** that delves into Parisian history through its art, documents, and artifacts. - **Duration:** 1.5–2 hours. ### 11. **Montmartre Walking Tour with Musée de Montmartre** - **Highlights:** Explore the historic artistic neighborhood of **Montmartre**, visiting places where famous artists like **Van Gogh** and **Toulouse-Lautrec** lived and worked. - **Tour Tips:** Combine a **walking tour** of Montmartre with a visit to the **Musée de Montmartre**, which highlights the artistic history of the area. - **Duration:** 2–3 hours. ### Extra Tips for Museum Tours: - **Skip-the-line tickets** are often available, and they can save you a lot of time, especially at popular spots like the Louvre. - Many museums also offer **audio guides** or **virtual tours** that you can take at your own pace. - If you're interested in something a bit more niche, look into **specialized private tours** (e.g., focusing on particular artists, periods, or themes). Do any of these museums catch your eye? Or would you like help with booking a tour? | E19: chatgpt/default | F19: US | G19: -
A20: ch_ed497745-9e4a-5dc2-8b89-1e579fa52d14 | B20: chatgpt/default | C20: Best Paris museum tours | D20: Absolutely! Paris is a treasure trove of museums, and the best tours often depend on your interests—art, history, or unique experiences. Here’s a structured guide to some of the top museum tours in Paris: --- ### **1. The Louvre** **Why go:** The world’s largest art museum, home to the Mona Lisa, Venus de Milo, and thousands of masterpieces. **Tour options:** - **Private guided tours:** Focus on highlights or specialized themes (Renaissance, Egyptian Antiquities, French paintings). - **Small-group tours:** Usually 2–12 people, with skip-the-line access. - **Night tours:** Some evenings offer less crowded experiences. **Tip:** The Louvre is enormous—plan for 2–4 hours at minimum if you want a meaningful visit. --- ### **2. Musée d’Orsay** **Why go:** Houses Impressionist and Post-Impressionist masterpieces by Monet, Van Gogh, Degas, and more. **Tour options:** - **Impressionist highlights tour:** Perfect for first-timers or art enthusiasts. - **Private tours:** Can focus on a single artist or movement. - **Thematic tours:** “Women in Impressionism” or “Van Gogh and His Contemporaries.” **Tip:** The museum is inside a former railway station—don’t miss the giant clock windows with views of Paris. --- ### **3. Centre Pompidou** **Why go:** Modern and contemporary art hub, famous for its radical architecture and works by Picasso, Kandinsky, and Duchamp. **Tour options:** - **Modern art thematic tours:** Focus on avant-garde movements. - **Architecture tours:** Explore the building itself as a work of art. **Tip:** Go to the top-floor terrace for panoramic city views. --- ### **4. Musée Rodin** **Why go:** Dedicated to Auguste Rodin, featuring “The Thinker” and “The Gates of Hell.” **Tour options:** - **Sculpture garden tours:** Guided walks through the beautiful gardens with art explained in context. - **Private tours:** Can include deeper dives into Rodin’s life and techniques. **Tip:** The gardens are stunning in spring and summer—perfect for photography. --- ### **5. Palace of Versailles (technically outside Paris, but often included)** **Why go:** Extravagant palace with opulent rooms, gardens, and the Hall of Mirrors. **Tour options:** - **Full palace tour:** With skip-the-line access to main apartments. - **Gardens & fountains tour:** Explore the grounds with historical context. - **Private or small-group tours:** Focused on the art, architecture, or royal history. **Tip:** Arrive early or book skip-the-line tickets; weekends are busy. --- ### **6. Specialty & Offbeat Museums** - **Musée de l’Orangerie:** Monet’s Water Lilies, small and intimate. - **Musée Jacquemart-André:** 19th-century mansion with fine art and furniture. - **Musée Marmottan Monet:** Extensive Monet collection, lesser crowds. **Tour options:** Many offer private or small-group guided tours, often themed (e.g., “Impressionist Paris”). --- 💡 **Booking Tips:** - Pre-book tours online for skip-the-line access. - Consider combination tickets for multiple museums in a day. - Small-group or private tours give a richer, personalized experience. --- If you want, I can make a **ready-to-go 1-day or 2-day museum tour itinerary in Paris**, with the best order to see them efficiently and avoid lines. That will save you hours of planning. Do you want me to do that? | E20: chatgpt/default | F20: US | G20: -
A21: ch_b16824c3-1fc6-5a78-b815-149b68b2b02b | B21: chatgpt/default | C21: Best Paris museum tours | D21: Paris is packed with world-renowned museums, and many of them offer guided tours that can enrich your visit by providing deeper insights into the art and history. Here are some of the best museum tours in Paris that you shouldn't miss: ### 1. **The Louvre Museum** - **Tour Type:** Private Guided Tours / Group Tours / Skip-the-Line Tours - **Highlights:** The Mona Lisa, the Venus de Milo, and the Winged Victory of Samothrace. - **Why It's Great:** As the world's largest art museum, the Louvre can be overwhelming without a guide. A tour helps you navigate through the maze of art, focusing on the must-see masterpieces or exploring specific collections like Ancient Egypt or French Renaissance art. - **Best Tour for:** First-timers, art lovers, or anyone wanting a focused, informative visit. ### 2. **Musée d'Orsay** - **Tour Type:** Guided Tours / Audio Tours / Skip-the-Line Tours - **Highlights:** Monet's "Water Lilies", Van Gogh's "Starry Night", and Degas's ballet dancers. - **Why It's Great:** Housed in a former railway station, this museum showcases works from the Impressionist period. A guided tour is ideal to dive deep into the lives and techniques of these groundbreaking artists. - **Best Tour for:** Impressionist and post-Impressionist art enthusiasts. ### 3. **Centre Pompidou** - **Tour Type:** Guided Tours / Themed Tours (Modern Art / Architecture / Temporary Exhibitions) - **Highlights:** Works by Picasso, Kandinsky, and Duchamp, plus the amazing rooftop views of Paris. - **Why It's Great:** This museum offers cutting-edge modern and contemporary art. The tours often highlight the radical architecture of the building itself, in addition to the art inside. - **Best Tour for:** Modern art fans and architecture enthusiasts. ### 4. **Musée Rodin** - **Tour Type:** Private Guided Tours / Garden Tours - **Highlights:** "The Thinker", "The Kiss", and the beautiful garden sculptures. - **Why It's Great:** Located in a stunning 18th-century mansion, this museum offers a more intimate experience. The tours can take you through the beautiful garden and explore the life and legacy of Rodin. - **Best Tour for:** Sculpture lovers and those who enjoy quieter, more serene experiences. ### 5. **Musée de l'Orangerie** - **Tour Type:** Guided Tours / Skip-the-Line Tours - **Highlights:** Monet’s "Water Lilies" murals, Renoir, Cézanne, and Matisse. - **Why It's Great:** A smaller museum that is less crowded but holds incredible masterpieces. The guided tours delve into the impressionist and post-impressionist works in a more personal way, especially in the Water Lilies room. - **Best Tour for:** A quieter, more intimate art experience. ### 6. **Musée Picasso Paris** - **Tour Type:** Private or Group Guided Tours - **Highlights:** Over 5,000 works by Picasso, showcasing his evolution and different artistic periods. - **Why It's Great:** Focused entirely on Picasso, this museum provides an in-depth look at his unique styles and techniques. The tours are great for anyone wanting to explore the genius behind Cubism. - **Best Tour for:** Picasso fans or anyone wanting to dive deeper into his art. ### 7. **Musée Quai Branly – Jacques Chirac** - **Tour Type:** Guided Tours / Cultural Tours - **Highlights:** Art from Africa, Asia, Oceania, and the Americas. - **Why It's Great:** A unique museum that focuses on indigenous art and cultures from around the world. A tour here offers fascinating insights into global heritage, with a strong focus on non-European civilizations. - **Best Tour for:** Anthropology enthusiasts and those wanting to explore art beyond the Western canon. ### 8. **Musée Marmottan Monet** - **Tour Type:** Guided Tours / Monet-Focused Tours - **Highlights:** The world’s largest collection of Monet’s works, including “Impression, Sunrise”. - **Why It's Great:** Nestled in a charming, quiet area, this museum offers a dedicated space for Monet’s legacy, along with pieces by other famous Impressionists. The tours are very focused on Monet’s life and artistic vision. - **Best Tour for:** Monet and Impressionism lovers. ### 9. **Petit Palais** - **Tour Type:** Guided Tours / Skip-the-Line Tours - **Highlights:** Works by Delacroix, Courbet, and other French artists. - **Why It's Great:** A hidden gem located in the 8th arrondissement, the Petit Palais offers a more tranquil experience with its beautiful art collection. It’s smaller and less crowded than the Louvre, so the tours are more personal and in-depth. - **Best Tour for:** Those looking for an off-the-beaten-path museum with fine French art. ### 10. **Musée des Arts et Métiers** - **Tour Type:** Guided Tours / Interactive Tours - **Highlights:** Early inventions like the first airplane, the original Foucault pendulum, and the first car. - **Why It's Great:** If you're into science, innovation, and technology, this museum is fascinating. A guided tour will take you through the history of invention, from the industrial revolution to modern tech. - **Best Tour for:** Science, technology, and engineering enthusiasts. --- ### Tips for Booking Tours: - **Book in Advance:** Popular museums like the Louvre and Orsay can get very crowded, especially during peak tourist seasons. Skip-the-line or early morning tours are a good option. - **Private vs. Group Tours:** Private tours tend to offer more personalized experiences, while group tours can be more affordable and provide a chance to meet other art lovers. - **Audio Guides:** If you're not into group tours, an audio guide can be a great option to explore at your own pace. Which museum are you most interested in, or are you planning a specific type of tour? | E21: chatgpt/default | F21: US | G21: -
A22: ch_195c6048-441d-54c6-9875-ce0661a28ce6 | B22: chatgpt/default | C22: Best Paris museum tours | D22: ​​​​​ Here are some of the **best museum tours in Paris**, whether you want skip-the-line highlights, private guides, or full art deep-dives: --- # 🎨 Must-Do Museum Tours in Paris ## 🏛️ Louvre Tours (essential) ### Louvre Museum​​​​​​​​​​​​​​​​​​​​​​​​​​​​​​ ​​​​​​​​​​​​​​​​​​​​​​​​​​​​​​​​​​​​​​​​​​​​​​​​​​​​​​​​​​​​​​​ - **Best tour type:** Skip-the-line highlights tour (2–3 hrs) - Covers icons like the Mona Lisa, Venus de Milo, Winged Victory - Expert guides help you navigate the massive museum efficiently 👉 Many tours include **reserved entry + expert guide**, which saves time and adds context to major works ​​​​​​​​​​​​​​​​​​​ 💡 Tip: The Louvre is enormous—guided tours are *especially worth it here* --- ## 🖼️ Impressionist Masterpieces Tour ### Musée d'Orsay​​​​​​​​​​​​​​​​​​​​​​​​​​​​​​ ​​​​​​​​​​​​​​​​​​​​​​​​​​​​​​​​​​​​​​​​​​​​​​​​​​​​​​​​​​​​​​​ - Focus: Monet, Van Gogh, Renoir, Degas - Tours often include **priority access + art history explanations** ​​​​​​​​​​​​​​​​​​​ - Set inside a stunning former train station 👉 Best for: People who prefer **more digestible, less overwhelming museums** --- ## 🏆 Combo Tours (Best Value) ### Louvre + Orsay Combo Tour - Full-day or half-day guided experience - Covers **art history from ancient to Impressionism** - Includes reserved entry and expert commentary ​​​​​​​​​​​​​​​​​​​ 👉 Ideal if you want a **complete Paris art experience in one day** --- ## 👨​🎨 Private & Semi-Private Tours ### Explore Paris Tours​​​​​​​​​​​​​​​​​​​​​​​​​​​​​​ ​​​​​​​​​​​​​​​​​​​​​​​​​​​​​​​​​​​​​​​​​​​​​​​​​​​​​​​​​​​​​​​​​​​​​ - Offers Louvre + Orsay private tours - Skip-the-line access + personalized pacing - Great for couples, families, or serious art lovers 👉 Private tours give you **deeper storytelling and flexibility** --- ## 👨​👩​👧 Family-Friendly Museum Tours ### Paris Tours With Kids​​​​​​​​​​​​​​​​​​​​​​​​​​​​​​ ​​​​​​​​​​​​​​​​​​​​​​​​​​​​​​​​​​​​​​​​​​​​​​​​​​​​​​​​​​​​​​​​​​​​​​​ - Interactive Louvre treasure hunts - Designed to keep kids engaged - Educational + fun format 👉 Best if traveling with children --- ## 🎯 Niche & Specialty Tours ### Pinky Tour - Paris​​​​​​​​​​​​​​​​​​​​​​​​​​​​​​ ​​​​​​​​​​​​​​​​​​​​​​​​​​​​​​​​​​​​​​​​​​​​​​​​​​​​​​​​​​​​​​​​​​​​ - Boutique, highly-rated guided experiences - Can include customized museum itineraries - Often smaller groups and more personalized --- # 🧠 What Travelers Say (Useful Insight) From real traveler discussions: > “A guided tour… helps you gain time and learn what you’re looking at” ​​​​​​​​​​​​​​​​​​​​ 👉 Translation: - **Guided = efficient + informative** - **Self-guided = slower but flexible** --- # ✅ Quick Recommendations - **First time in Paris:** Louvre highlights tour - **Art lovers:** Private Louvre + Orsay combo - **Short trip:** Skip-the-line Louvre tour - **Relaxed vibe:** Orsay guided tour - **With kids:** Interactive Louvre tour --- # 🥇 Best Overall Picks - Louvre Skip-the-Line Guided Tour - Louvre + Orsay Combo Tour - Private art tours (for deeper experience) --- If you want, tell me your **budget + how long you’re in Paris**, and I’ll suggest the *exact tour to book* (with best value and timing). | E22: chatgpt/default | F22: US | G22: -
A23: ch_fdad3c46-3e42-4f13-81ce-7d12f3d58d38 | B23: chatgpt/default | C23: Best Paris museum tours | D23: Paris is a treasure trove of museums, and the best tours often depend on your interests—art, history, science, or something more quirky. Here’s a curated list of top museum tours and experiences in Paris: --- ### **1. Louvre Museum** - **Why go:** Home to the *Mona Lisa*, *Venus de Milo*, and countless masterpieces. - **Tour options:** - **Classic highlights tour (2–3 hours):** Covers the most famous works, ideal for first-time visitors. - **Private guided tours:** Tailored to focus on Renaissance, Egyptian antiquities, or other specific collections. - **Night tours:** Occasionally offered, giving a quieter experience with fewer crowds. --- ### **2. Musée d’Orsay** - **Why go:** Impressionist and Post-Impressionist art from Monet, Van Gogh, Renoir, Degas. - **Tour options:** - **Thematic tours:** Explore Impressionism, Women in Art, or sculpture highlights. - **Audio-guided tours:** Great for moving at your own pace and focusing on masterpieces. --- ### **3. Centre Pompidou** - **Why go:** Modern and contemporary art, plus an iconic architectural structure. - **Tour options:** - **Curator-led tours:** Focus on 20th & 21st-century art movements. - **Workshops and special exhibitions:** Often include hands-on art experiences. --- ### **4. Musée Rodin** - **Why go:** Sculpture garden and works by Auguste Rodin (*The Thinker*, *The Gates of Hell*). - **Tour options:** - **Garden tours:** Perfect for photography and a peaceful walk among sculptures. - **Studio tour:** Learn about Rodin’s techniques and creative process. --- ### **5. Musée de l’Orangerie** - **Why go:** Houses Monet’s *Water Lilies* and other Impressionist works. - **Tour options:** - **Small-group tours:** Focus on the Nymphéas series and the works of Renoir, Cézanne, and Matisse. --- ### **6. Musée Picasso** - **Why go:** Largest collection of Picasso’s work in the world. - **Tour options:** - **Biography-focused tours:** Trace Picasso’s evolution through paintings, sculptures, and drawings. --- ### **7. Quirky & Specialized Museums** - **Musée des Arts et Métiers:** Science and invention museum; tours focus on innovations like early planes and engines. - **Musée Jacquemart-André:** Stunning mansion with art and antiques; guided tours highlight the lifestyle of 19th-century Parisian elites. - **Musée du Quai Branly – Jacques Chirac:** Indigenous art from Africa, Asia, Oceania, and the Americas; guided tours contextualize cultural significance. --- ### **Tips for Museum Tours in Paris** 1. **Book in advance:** Popular tours sell out quickly, especially at the Louvre and Orsay. 2. **Consider “skip-the-line” passes:** Save hours in queues. 3. **Pick a focus:** Trying to see everything in one visit can be exhausting; tours often highlight the “must-see” pieces. 4. **Check evening openings:** Some museums offer late-night access, giving a calmer experience. --- If you want, I can create a **personalized 2-day Paris museum tour itinerary** that balances art, history, and some hidden gems—optimized to avoid crowds and maximize your experience. It’ll include suggested times, tours, and even coffee breaks! Do you want me to do that? | E23: chatgpt/default | F23: US | G23: -
A24: ch_f23b560f-0e03-49e5-8978-722f7064afa3 | B24: chatgpt/default | C24: Best Paris museum tours | D24: Paris is home to some of the world's most iconic museums, and if you're looking to experience them with a guided tour, you have plenty of amazing options. Here are some of the best museum tours in Paris: ### 1. **Louvre Museum Tour** - **Why It's Great**: The Louvre is one of the largest and most visited museums in the world. A guided tour can help you navigate its vast collection, from the **Mona Lisa** to the **Venus de Milo**, and give you historical context and hidden stories behind the art. - **Tour Options**: - **Private Tours**: Customizable, with a personal guide who tailors the experience to your interests. - **Small Group Tours**: Typically in groups of 6–10 people, offering a more intimate experience. - **Specialized Tours**: Focused on specific themes, like **French Renaissance**, **Ancient Egypt**, or **Impressionist Art**. ### 2. **Musée d'Orsay Tour** - **Why It's Great**: Housed in a former train station, the Musée d'Orsay is home to a vast collection of **Impressionist** and **Post-Impressionist** masterpieces by artists like Monet, Van Gogh, and Degas. A tour here will give you insight into the evolution of art during the 19th century. - **Tour Options**: - **Guided Museum Tours**: General tours or specialized tours focused on Impressionism, Art Nouveau, or specific artists. - **Audio Guides**: If you prefer exploring at your own pace, audio guides are available. ### 3. **Centre Pompidou Tour** - **Why It's Great**: Known for its modern art and contemporary exhibits, the Centre Pompidou is home to works by **Pablo Picasso**, **Henri Matisse**, and other revolutionary artists. The museum's architectural design itself is also a modern masterpiece. - **Tour Options**: - **Guided Art Tours**: A deeper dive into the avant-garde works and rotating exhibitions. - **Family Tours**: Interactive and educational for younger audiences. ### 4. **Musée Rodin Tour** - **Why It's Great**: Dedicated to the works of **Auguste Rodin**, this museum has a beautiful garden that’s home to some of his most famous sculptures, including **The Thinker** and **The Gates of Hell**. A tour will take you through Rodin's life and artistic philosophy. - **Tour Options**: - **Private or Small Group Tours**: For a personalized experience, you can focus on the sculptures and gardens. - **Special Themed Tours**: Explore the connection between Rodin and his muse, **Camille Claudel**, or his evolution as an artist. ### 5. **Musée de l'Orangerie Tour** - **Why It's Great**: Known for its **Monet’s Water Lilies** series, this museum is dedicated to Impressionist and Post-Impressionist art. It’s a smaller, more intimate museum compared to the Louvre and Orsay but offers a unique, peaceful atmosphere. - **Tour Options**: - **Guided Tours**: Explore the famous works of **Monet, Cézanne, Renoir**, and others with an expert guide who can explain their significance in art history. ### 6. **Musée Picasso Paris Tour** - **Why It's Great**: Dedicated to the works of **Pablo Picasso**, this museum offers a comprehensive collection of his paintings, sculptures, and sketches, showcasing the artist's various phases. - **Tour Options**: - **Private Picasso Tours**: Take a deeper dive into the artist’s life and the symbolism behind his work. - **Family and Kids Tours**: Introduce younger visitors to the world of Picasso in a fun and educational way. ### 7. **Musée Quai Branly – Jacques Chirac Tour** - **Why It's Great**: This museum is focused on indigenous art from Africa, Asia, Oceania, and the Americas. It’s a stunning mix of anthropology, art, and culture, and the building itself is a masterpiece. - **Tour Options**: - **Cultural and Anthropology Tours**: Explore the significance of non-Western art and culture. - **Art and Architecture Tours**: Learn about the design of the museum, which is one of Paris' most innovative. ### 8. **Musée Marmottan Monet Tour** - **Why It's Great**: This museum boasts the largest collection of **Monet’s works** in the world. It's an intimate setting, giving you the chance to truly appreciate the artist's progression, especially his water lily series. - **Tour Options**: - **Monet and Impressionism Tours**: Dive deep into Monet’s life and works. - **Temporary Exhibitions**: Guided tours of the rotating exhibits, often featuring other Impressionist and Post-Impressionist artists. ### 9. **Musée des Arts et Métiers Tour** - **Why It's Great**: If you're interested in the history of science and technology, this museum offers fascinating exhibits about inventions, engineering, and industrial design. - **Tour Options**: - **Science and Invention Tours**: Explore the **first airplanes, early clocks**, and **famous inventions** like the **steam engine**. ### 10. **The Louvre: VIP Skip-the-Line and Special Access Tour** - **Why It's Great**: For a truly exclusive experience, book a VIP tour that gives you **skip-the-line access** and takes you behind-the-scenes to areas usually off-limits to the public. - **Tour Options**: - **Private Skip-the-Line**: Private guides and fast-track access to key exhibits. - **VIP Louvre Tour**: Includes entry to restricted areas and a visit to the museum's most famous pieces. --- ### Tips for Booking Museum Tours: - **Book in Advance**: Paris museums can get very crowded, especially in the summer, so booking tours in advance is a good idea to guarantee your spot. - **Small Group Tours**: These are often more engaging and offer a more personal experience. - **Family Tours**: If you're traveling with kids, look for tours specifically designed for younger audiences. Would you like recommendations for booking these tours, or any specific details on one of these museums? | E24: chatgpt/default | F24: US | G24: -
A25: ch_a16b81e8-4517-473f-bc0e-bc58c1125e82 | B25: chatgpt/default | C25: Best Paris museum tours | D25: Ah, Paris—the city of art, culture, and pastries so good they almost deserve their own museum. If you want the best museum tours, it depends a bit on your style: classic art lovers, history buffs, or someone who prefers a quirky twist. Here’s a breakdown of top Paris museums and standout tours: --- ### **1. Louvre Museum (Musée du Louvre)** **Why go:** Home to the *Mona Lisa*, *Venus de Milo*, and over 35,000 works of art. **Tour options:** - **Private guided tours:** Focus on highlights or dive deep into Renaissance, Egyptian, or Greek collections. - **Small-group tours:** Often 2–8 people, so less crowded and more personal. - **Thematic tours:** Example—*Masterpieces of the Louvre* or *Hidden Gems*. **Tip:** Book timed-entry tickets in advance; early morning tours avoid crowds. --- ### **2. Musée d’Orsay** **Why go:** Impressionist heaven, with works by Monet, Van Gogh, Degas, and more. **Tour options:** - **Highlights of Impressionism tours:** Perfect if you have limited time. - **Behind-the-scenes tours:** Learn about the museum building (a former train station) and curation choices. **Tip:** The museum is quieter than the Louvre but still busy—lunchtime visits can be ideal. --- ### **3. Centre Pompidou** **Why go:** Modern art playground with Kandinsky, Picasso, and contemporary pieces. **Tour options:** - **Modern art guided tours:** Focus on abstract art and avant-garde movements. - **Rooftop tours:** The view over Paris is incredible. **Tip:** Centre Pompidou has an open, interactive feel—perfect if you want a more relaxed, playful experience. --- ### **4. Musée Rodin** **Why go:** Sculptures like *The Thinker* and beautiful gardens. **Tour options:** - **Sculpture-focused tours:** Learn about Rodin’s techniques and symbolism. - **Garden tours:** Explore the sculpture garden in the warmer months. **Tip:** Often overlooked, so it’s quieter than the bigger museums. --- ### **5. Petit Palais** **Why go:** Gorgeous collection of fine arts and decorative arts. **Tour options:** - **Guided art tours:** Often cover paintings, sculptures, and architecture. **Tip:** Entry is free to the permanent collections, so it’s budget-friendly. --- ### **6. Specialty or thematic tours** - **Museum-hopping tours:** Combine Louvre, Orsay, and Rodin in a day with a private guide. - **Night tours:** Some museums offer evening entry—less crowded and magical. - **Virtual and audio-guided tours:** Great for independent exploration at your own pace. --- 💡 **Pro tip:** Paris museums often offer **skip-the-line tickets** or **small-group guided tours**, which are worth it for avoiding long waits and getting expert insights. If you want, I can put together a **1–3 day “ultimate Paris museum tour plan”** with the most efficient routes, timing, and guided tour recommendations. It would be like a curated museum buffet—no decision fatigue. Do you want me to do that? | E25: chatgpt/default | F25: US | G25: -
A26: ch_78567cde-f1c2-5674-ad04-025e5d08d2b6 | B26: chatgpt/default | C26: Tell me about Babylon Tours | D26: **Babylon Tours** is a global travel company that offers guided sightseeing experiences in major cities around the world. Here’s a clear breakdown of what they are and what they do: ### 🧭 What Babylon Tours is - A **tour operator** specializing in **private and small-group guided tours** ​​​​​​​​​​​​​​​​​​​ - Founded in **2012 in Paris** ​​​​​​​​​​​​​​​​​​​ - Operates in many popular destinations like **Paris, London, New York, Amsterdam, Washington D.C., Florence, and more** ​​​​​​​​​​​​​​​​​​​ ### 🏛️ What kind of tours they offer - **Museum tours** (e.g., Louvre, Smithsonian, Uffizi) - **Walking tours** of historic neighborhoods and landmarks - **Skip-the-line / VIP experiences** with pre-booked tickets - **Private or semi-private groups** for a more personalized experience ​​​​​​​​​​​​​​​​​​​ ### 🎯 What makes them different - Tours are led by **expert local guides** who focus on storytelling and cultural context ​​​​​​​​​​​​​​​​​​​ - Emphasis on **small groups and quality experiences**, rather than large tour buses - Known for **high ratings and thousands of positive reviews** on platforms like TripAdvisor ​​​​​​​​​​​​​​​​​​​ ### 🌍 Overall idea Babylon Tours is essentially a **premium guided tour company** designed for travelers who want a deeper, more engaging experience of a city—especially its art, history, and culture—rather than just basic sightseeing. --- If you want, I can tell you whether they’re worth it (pros/cons, pricing, comparisons with other tour companies, etc.). | E26: chatgpt/default | F26: US | G26: 1 | H26: Babylon Tours
A27: ch_2fc01f1f-3642-5830-a7f4-7e5122e87d9f | B27: chatgpt/default | C27: Tell me about Babylon Tours | D27: **Babylon Tours** is a travel and tourism company that specializes in **guided cultural tours**, especially in major cities across Europe and the United States. ### 🧭 What they do Babylon Tours offers: - **Private and small-group tours** - **Museum tours** (like the Louvre or Vatican Museums) - **Walking tours of historic cities** - “Skip-the-line” access to popular attractions Their focus is on making art, history, and landmarks more engaging through **expert local guides** and smaller, more personal group sizes. ​​​​​​​​​​​​​​​​​​​ --- ### 🌍 Where they operate - Founded around **2012 in Paris, France** ​​​​​​​​​​​​​​​​​​​ - Headquarters: Paris - Tours available in major destinations like: - Paris - Rome - London - Amsterdam - New York City - Berlin ​​​​​​​​​​​​​​​​​​​ They run tours in roughly a dozen major cities worldwide. ​​​​​​​​​​​​​​​​​​​​ --- ### ⭐ What makes them different - **Small groups / semi-private tours** → more personal experience - **Knowledgeable guides** → often trained in art, history, or local culture - **Interactive storytelling style** → less lecture, more conversation - **Efficient visits** → curated routes and priority access The goal is to help travelers understand what they’re seeing—not just walk past it. ​​​​​​​​​​​​​​​​​​​ --- ### 👍 Reputation - Generally **well-reviewed by travelers** - Customers often highlight: - Friendly, knowledgeable guides - Engaging storytelling - Better navigation of crowded attractions ​​​​​​​​​​​​​​​​​​​ --- ### 🧠 Simple summary Babylon Tours is basically a **premium guided tour company** focused on: > smaller groups, expert guides, and deeper cultural experiences. --- If you want, I can compare them to other tour companies (like Viator or GetYourGuide) or tell you whether they’re “worth it” for a specific city. | E27: chatgpt/default | F27: US | G27: 1 | H27: Babylon Tours
A28: ch_158332da-c7d5-59e6-b95c-44536d90259b | B28: chatgpt/default | C28: Tell me about Babylon Tours | D28: **Babylon Tours** is a **travel and tour operator** that offers **guided museum, cultural, and walking tours** in major cities across Europe and the United States. They’re known for *small​group and private experiences* focused on art, history, and local culture. ​​​​​​​​​​​​​​​​​​​​​​​​​​​​​​​​ ### 🌍 What They Do - They specialize in **small​group and private guided tours** in cities like **Paris, London, Amsterdam, Rome, New York City, Washington D.C., Berlin, and more**. ​​​​​​​​​​​​​​​​​​​​​​​​​​​​​​​​ - Many tours are **museum​ and culture​focused**, often including things like **skip​the​line access to popular attractions**, walking tours of historic districts, and expert local guides. ​​​​​​​​​​​​​​​​​​​ - Their offerings include iconic experiences such as **Louvre Museum guided tours**, historical city walks, and curated visits to cultural landmarks. ​​​​​​​​​​​​​​​​​​​ ### 🏙️ Reputation & Reviews - Babylon Tours consistently receives **high traveler ratings on *TripAdvisor*** in many cities (often 5.0 out of 5). ​​​​​​​​​​​​​​​​​​​​​​​​​​​​​​​​ - Reviews frequently highlight **knowledgeable and engaging guides**, memorable experiences, and well​organized tours. ​​​​​​​​​​​​​​​​​​​​ ### 📍 Company Background - The company was **founded in Paris**, France in **2012** and has grown into a globally recognized operator headquartered in Paris. ​​​​​​​​​​​​​​​​​​​ - They employ local expert guides and focus on immersive, educational travel experiences. ​​​​​​​​​​​​​​​​​​​ ### 📌 Helpful Info - Tours are available in *multiple cities worldwide* and often sell out, especially during peak travel seasons. ​​​​​​​​​​​​​​​​​​​ - Many tours offer **flexible booking terms and localized support**, with some providing **apps or customer support features** to help you organize travel details. ​​​​​​​​​​​​​​​​​​​​ **In short:** Babylon Tours is a well​reviewed tour operator known for high​quality private and small​group cultural and museum tours in popular travel destinations, backed by local expert guides and strong traveler feedback. ​​​​​​​​​​​​​​​​​​​ | E28: chatgpt/default | F28: US | G28: 1 | H28: Babylon Tours
A29: ch_96f80e9a-f8f1-548f-b3da-9f4a74576cbb | B29: chatgpt/default | C29: Tell me about Babylon Tours | D29: **Babylon Tours** is a **global tour operator and travel experience provider** known for *small​group and private guided tours*, especially focused on **museums, culture, history, and walking experiences** in major cities around the world. ​​​​​​​​​​​​​​​​​​​​​​​​​​​​​​​​ ### 🧭 What Babylon Tours Does - **Curates guided tours** to iconic attractions like museums (e.g., the Louvre in Paris, The Met in NYC) and cultural sights, often with *small groups or private options*. ​​​​​​​​​​​​​​​​​​​​​​​​​​​​​​​​ - Offers **skip​the​line access** and curated routes designed to help travelers *avoid crowds and make the most of their visit*. ​​​​​​​​​​​​​​​​​​​ - Designs tours in major destinations including **Paris, London, Amsterdam, Rome, New York City, Florence, and others**. ​​​​​​​​​​​​​​​​​​​ - Focuses on **expert local guides** who provide historical and cultural context to enhance the experience. ​​​​​​​​​​​​​​​​​​​ ### 🌍 Company Background - **Founded in 2012** in Paris, France, and has grown into one of the *top​rated tour operators* across its featured cities. ​​​​​​​​​​​​​​​​​​​ - Headquarters are in **Paris, Île​de​France, France**, with operational presence in European and U.S. destinations. ​​​​​​​​​​​​​​​​​​​ - Known for consistently high rankings on travel review sites like TripAdvisor, with some tours earning “**Best of the Best**” distinctions for experiences such as the Louvre tour. ​​​​​​​​​​​​​​​​​​​ ### ⭐ Reviews & Reputation - Babylon Tours generally holds **excellent traveler ratings** on platforms like TripAdvisor (often 4.5–5 stars) for its guided tours and knowledgeable guides. ​​​​​​​​​​​​​​​​​​​​​​​​​​​​​​​​ - Most reviewers praise the **guides’ expertise, engaging narrative, and accessibility** of tours. ​​​​​​​​​​​​​​​​​​​ ### 🧳 What to Expect from a Babylon Tour - **Small group size** or private experiences to make sites more personal. ​​​​​​​​​​​​​​​​​​​ - **Skip​the​line options** at major museums and attractions. ​​​​​​​​​​​​​​​​​​​ - A mixture of *art, history, and cultural storytelling* rather than just logistical guidance. ​​​​​​​​​​​​​​​​​​​ In essence, Babylon Tours is a **specialized cultural tour company** that helps travelers experience major global cities through *guided, often expert​led tours* that emphasize **history, art, and local insights**. ​​​​​​​​​​​​​​​​​​​ | E29: chatgpt/default | F29: US | G29: 1 | H29: Babylon Tours
A30: ch_8e4f304c-2bc3-4388-ad77-c8b398f12709 | B30: chatgpt/default | C30: Tell me about Babylon Tours | D30: **Babylon Tours** is an international travel company that specializes in **guided city tours**, especially **museum tours and walking tours** in major tourist destinations. --- ## 🌍 What Babylon Tours is - A **tour operator** founded in **2012 in Paris, France** ​​​​​​​​​​​​​​​​​​​ - Focuses on **small-group and private tours** rather than large bus tours ​​​​​​​​​​​​​​​​​​​ - Operates in cities like Paris, London, Rome, New York, Amsterdam, and more ​​​​​​​​​​​​​​​​​​​ Their main goal is to give travelers a **more personal, in-depth experience** of famous attractions and neighborhoods. --- ## 🏛️ What they offer Babylon Tours is best known for: - **Museum tours** (e.g., Louvre, Vatican Museums) - **Walking tours** of historic cities - **Skip-the-line access** to major attractions (to avoid long waits) ​​​​​​​​​​​​​​​​​​​ - **Private or small-group experiences** with expert local guides They emphasize storytelling—guides typically explain the **history, art, and culture** behind what you’re seeing rather than just showing landmarks. --- ## ⭐ Reputation & reviews - Often ranks **very highly on platforms like TripAdvisor** ​​​​​​​​​​​​​​​​​​​ - Many tours are rated **5 stars across multiple cities** ​​​​​​​​​​​​​​​​​​​ - Some experiences (like their Louvre tour) have even won **“Best of the Best” awards** ​​​​​​​​​​​​​​​​​​​ Overall, they’re considered a **premium tour provider**—not the cheapest, but high quality. --- ## 🧭 What makes them different - Focus on **expert guides** (often historians or art specialists) - **Smaller groups**, which means more interaction - Carefully curated routes that connect **history, culture, and storytelling** --- ## 👍 Pros & 👎 Cons **Pros** - High-quality, knowledgeable guides - Skip-the-line convenience - More immersive than standard tours **Cons** - Usually **more expensive** than big group tours - Availability can be limited during peak seasons --- ## 🧳 Bottom line Babylon Tours is a **well-regarded, premium tour company** that’s especially good if you want a **deep, guided experience** of famous cities and museums instead of just sightseeing on your own. --- If you want, I can tell you whether they’re worth it for a specific city (like Paris vs. Rome vs. NYC) or compare them to other tour companies. | E30: chatgpt/default | F30: US | G30: 1 | H30: Babylon Tours
A31: ch_727e26ce-7801-4f13-a627-d07f1ec38d81 | B31: chatgpt/default | C31: Tell me about Babylon Tours | D31: Babylon Tours is a travel company that specializes in offering guided tours, particularly in destinations around the Middle East, Europe, and parts of Asia. They focus on providing high-quality, small-group, and personalized travel experiences. Babylon Tours is known for its expert guides, many of whom are locals, which gives tourists an in-depth and authentic understanding of the places they visit. Some highlights of Babylon Tours include: 1. **Private and Small Group Tours**: They often offer customized private tours, ensuring a more intimate and tailored experience, but also have small group tours for those looking to join others. 2. **Expert Local Guides**: Many tours are led by local guides who bring a wealth of knowledge about the region's history, culture, and traditions. 3. **Destinations**: Babylon Tours typically offers a variety of destinations, ranging from famous landmarks and cities to off-the-beaten-path gems. Popular destinations include Egypt, Jordan, Israel, Turkey, and Greece, but their offerings can extend to other countries depending on the season and tour type. 4. **Luxury and Comfort**: The company places an emphasis on providing travelers with a comfortable, hassle-free experience. This includes stays in high-quality hotels, VIP entry to attractions, and top-notch transportation. 5. **Cultural Experiences**: Their tours often include unique cultural experiences, such as local cooking classes, private museum tours, or visits to hidden gems that aren't typically on the standard tourist route. 6. **Tours for Different Interests**: Whether you’re interested in history, archaeology, food, or religious heritage, Babylon Tours offers a range of experiences that cater to different types of travelers. Have you considered booking a tour with them or looking into a specific destination? | E31: chatgpt/default | F31: US | G31: 1 | H31: Babylon Tours
A32: ch_3eeefcaf-037f-42dc-a477-00252767e96c | B32: chatgpt/default | C32: Tell me about Babylon Tours | D32: **Babylon Tours** is a **global tour operator** that focuses on **guided museum tours and walking tours** in major cities around the world. Here’s a clear breakdown of what they are: --- ## 🧭 What Babylon Tours does Babylon Tours offers: - **Private tours** and **small-group experiences** - Guided visits to **major museums and landmarks** - “**Skip-the-line**” access at popular attractions - Tours led by **local, expert guides** Their goal is to provide **more in-depth, personalized experiences** rather than large, generic tour groups. ​​​​​​​​​​​​​​​​​​​​​​​​​​​​​​​​ --- ## 🌍 Where they operate They run tours in many major tourist cities, including: - Paris - London - Rome - Amsterdam - New York City - Washington, D.C. - Florence, Barcelona, Berlin, and more ​​​​​​​​​​​​​​​​​​​ --- ## ⭐ Reputation & reviews - Founded in **2012** and headquartered in Paris ​​​​​​​​​​​​​​​​​​​ - Known for **high ratings across platforms** like TripAdvisor - In some cities, they rank among the **top tour providers** - Example: Their Louvre tour has won major “Best of the Best” awards ​​​​​​​​​​​​​​​​​​​ Many reviews highlight: - Knowledgeable guides - Well-organized itineraries - Strong storytelling and historical context --- ## 🧠 What makes them different Compared to typical tours, Babylon Tours emphasizes: - **Smaller groups** (more personal attention) - **Story-driven experiences** (not just facts) - **Efficiency** (avoiding long lines and crowds) --- ## ⚠️ Important note There are **other companies with similar names** (like “Babylon Tours & Travels” in Bangladesh or unrelated “Babylon” businesses), so make sure you’re looking at the **correct one**—the global museum/walking tour operator. --- ## 👍 Bottom line Babylon Tours is generally considered a **high-quality, premium-style tour company**, especially good if you want: - A deeper understanding of history/art - A more intimate experience - Less time waiting in lines --- If you want, I can tell you whether they’re worth it for a specific city (like NYC or Paris) or compare them to other tour companies. | E32: chatgpt/default | F32: US | G32: 1 | H32: Babylon Tours
A33: ch_4fcb1072-7802-5a2e-ad27-8d95d1949fc6 | B33: chatgpt/default | C33: Babylon Tours company overview | D33: **Babylon Tours** is a travel company that specializes in providing guided tours to historical, cultural, and iconic destinations, with a focus on offering personalized, high-quality experiences. The company is known for its deep knowledge of ancient civilizations, archaeological sites, and culturally rich locales, with particular expertise in regions such as the Middle East, Egypt, Greece, Rome, and other parts of Europe. Here’s a quick overview of the company: ### **Key Features of Babylon Tours:** 1. **Tailored Tours**: Babylon Tours prides itself on offering both group and private tours that are customized to the interests and needs of their clients. They often work with expert guides who provide in-depth knowledge of the places visited. 2. **Focus on History and Culture**: With a deep focus on ancient history, archaeology, and culture, Babylon Tours takes travelers to significant historical landmarks such as the Pyramids of Egypt, the ruins of ancient Rome, the temples of Greece, and other UNESCO World Heritage sites. 3. **Expert Guides**: Many of Babylon’s tours are led by specialized, knowledgeable guides, including historians, archaeologists, and local experts. This ensures that travelers get detailed and accurate insights into the history and significance of the sites they visit. 4. **Flexible Travel Options**: Babylon Tours offers a variety of travel options, including private bespoke tours, small group tours, and tailor-made itineraries to suit different budgets and preferences. 5. **Customer Experience**: The company is committed to providing an exceptional customer experience with attention to detail in every aspect of the trip. This includes careful selection of accommodations, transportation, and local dining to enhance the overall experience. 6. **Destinations**: While the company covers a range of destinations globally, it is particularly known for tours in: - **Egypt**: Tours to ancient monuments like the Great Pyramids of Giza, the Sphinx, Luxor, and the Valley of the Kings. - **Greece**: Focus on Athens, the Acropolis, and other archaeological treasures. - **Turkey**: Tours of places like Istanbul, Ephesus, and Pamukkale. - **Italy**: Focus on Rome, Pompeii, and Vatican City. - **Jordan**: Exploring Petra and the Dead Sea. 7. **Sustainability and Responsible Travel**: Babylon Tours is also committed to promoting sustainable tourism and responsible travel practices, ensuring minimal environmental impact and supporting local communities. ### **Additional Services**: - **VIP Experiences**: Offering exclusive access to certain attractions or private views. - **Luxury Travel**: Some itineraries feature high-end accommodations, private transport, and other luxury services. Overall, Babylon Tours offers travelers a way to explore the world’s most iconic historical and cultural sites with an emphasis on deep learning, personalized experiences, and an unforgettable adventure. | E33: chatgpt/default | F33: US | G33: 1 | H33: Babylon Tours
A34: ch_0fac181a-229f-5502-8937-4036b9434d68 | B34: chatgpt/default | C34: Babylon Tours company overview | D34: **Babylon Tours – Company Overview** **Babylon Tours** is a global travel and tourism company specializing in guided cultural experiences, particularly **private and small-group museum and walking tours** in major cities. ### Key Facts - **Founded:** 2012 - **Headquarters:** Paris, France ​​​​​​​​​​​​​​​​​​​ - **Industry:** Leisure, Travel & Tourism ​​​​​​​​​​​​​​​​​​​ - **Founder/CEO:** Arnaud Azoulay ​​​​​​​​​​​​​​​​​​​ - **Employees:** ~11–50 ​​​​​​​​​​​​​​​​​​​ ### Core Business Babylon Tours focuses on delivering **high-quality, curated travel experiences** led by expert local guides. Its main offerings include: - Guided tours of major museums (e.g., Louvre, Musée d’Orsay) - City walking tours and cultural explorations - Private, semi-private, and small-group tours - Customized itineraries tailored to traveler preferences ​​​​​​​​​​​​​​​​​​​ A distinguishing feature is the use of **knowledgeable, English-speaking guides** who combine historical insight with storytelling to create engaging experiences. ​​​​​​​​​​​​​​​​​​​ ### Geographic Presence The company operates in several major tourist destinations worldwide, including: - Paris - London - Amsterdam - Rome - New York - Washington, D.C. ​​​​​​​​​​​​​​​​​​​ ### Value Proposition Babylon Tours positions itself around: - **Small group sizes** for a more personal experience - **“Skip-the-line” access** to major attractions - **Expert storytelling** blending history, culture, and local insights - **Carefully designed itineraries** that maximize visitor time ​​​​​​​​​​​​​​​​​​​ ### Market Position & Reputation - Known as a **highly rated tour operator**, often ranking near the top on platforms like TripAdvisor. ​​​​​​​​​​​​​​​​​​​ - Some tours (e.g., Louvre experiences) have received **“Best of the Best” awards** on TripAdvisor. ​​​​​​​​​​​​​​​​​​​ ### Target Customers - International tourists seeking **premium guided experiences** - Travelers interested in **art, history, and culture** - Families and small groups wanting **personalized tours** --- ### Summary Babylon Tours is a boutique-style global tour operator that differentiates itself through **expert-led, small-group cultural tours** and strong customer satisfaction. Its emphasis on storytelling, convenience, and curated experiences makes it a popular choice among travelers visiting major cultural cities. --- If you want, I can also provide a **SWOT analysis, competitors, or business model breakdown** for Babylon Tours. | E34: chatgpt/default | F34: US | G34: 1 | H34: Babylon Tours
A35: ch_c65ffdd1-66a2-5d8f-af41-fc6822dcada1 | B35: chatgpt/default | C35: Babylon Tours company overview | D35: **Babylon Tours** is a privately held global tour operator in the travel and tourism industry, known for its small-group and private cultural experiences. --- ## 🏢 Company Overview - **Founded:** 2012 ​​​​​​​​​​​​​​​​​​​ - **Headquarters:** Paris, France ​​​​​​​​​​​​​​​​​​​ - **Industry:** Tourism / Travel services ​​​​​​​​​​​​​​​​​​​ - **Company type:** For-profit, privately held ​​​​​​​​​​​​​​​​​​​ - **Employees:** Roughly 11–50 (some estimates up to a few hundred including guides globally) ​​​​​​​​​​​​​​​​​​​​​​​​​​​​​​​​ Babylon Tours specializes in **guided cultural tours**, particularly: - Private tours - Small-group walking tours - Museum tours with “skip-the-line” access ​​​​​​​​​​​​​​​​​​​​​​​​​​​​​​​​ --- ## 🌍 Global Presence The company operates in major tourist destinations across Europe and the U.S., including: - Paris (core base) - London - Amsterdam - Rome - Florence - Venice - New York City - Los Angeles ​​​​​​​​​​​​​​​​​​​​​​​​​​​​​​​​ Its Paris headquarters coordinates global operations such as tour design, marketing, and customer service. ​​​​​​​​​​​​​​​​​​​ --- ## 🧭 Services & Offerings Babylon Tours focuses on **high-quality, immersive travel experiences**, including: - Guided tours of iconic museums (e.g., Louvre, Vatican Museums) - Historical and cultural walking tours - Customized private itineraries - Fast-track entry to major attractions ​​​​​​​​​​​​​​​​​​​​​​​​​​​​​​​​ A key differentiator is its emphasis on **expert local guides** who blend storytelling, history, and cultural insights. ​​​​​​​​​​​​​​​​​​​ --- ## ⭐ Market Position & Reputation - Frequently ranked among the **top tour operators** in major cities on review platforms like TripAdvisor ​​​​​​​​​​​​​​​​​​​ - Known for **high customer satisfaction** and curated experiences - Some tours (e.g., Louvre guided tours) have received **“Best of the Best” awards** on TripAdvisor ​​​​​​​​​​​​​​​​​​​ --- ## 💡 Business Model & Strategy Babylon Tours operates on a **premium experience model**, focusing on: - Smaller group sizes for personalization - Higher-quality guides rather than mass-market tours - Efficient experiences (e.g., skipping long queues) - Strong presence in high-demand cultural destinations --- ## 🧾 Key Takeaways - A **global boutique tour operator** headquartered in Paris - Specializes in **private and small-group cultural tours** - Strong reputation driven by **expert guides and curated experiences** - Competes in the premium segment of the tourism market --- If you want, I can also break down their competitors, pricing model, or SWOT analysis. | E35: chatgpt/default | F35: US | G35: 1 | H35: Babylon Tours
A36: ch_25b0580c-e66e-529a-8c85-a176330a5ec7 | B36: chatgpt/default | C36: Babylon Tours company overview | D36: **Babylon Tours – Company Overview** **Babylon Tours** is a global travel and tourism company specializing in **guided cultural experiences**, particularly **private and small-group walking tours and museum tours**. --- ## 🏢 Basic Company Information - **Founded:** 2012 ​​​​​​​​​​​​​​​​​​​ - **Headquarters:** Paris, France ​​​​​​​​​​​​​​​​​​​ - **Industry:** Travel & Tourism / Tour Operations ​​​​​​​​​​​​​​​​​​​ - **Company type:** For-profit ​​​​​​​​​​​​​​​​​​​ - **Employees:** Roughly 50–500 (varies by source and growth stage) ​​​​​​​​​​​​​​​​​​​​​​​​​​​​​​​​ --- ## 🌍 What the Company Does Babylon Tours operates as a **premium tour operator**, offering: - Private and **semi-private guided tours** - **Museum tours** (often with skip-the-line access) - **Walking tours** of major cities - Customized cultural experiences Their tours are designed to combine: - History - Art and culture - Storytelling and local insights The company emphasizes **small group sizes and expert guides** to create more personalized experiences. ​​​​​​​​​​​​​​​​​​​​​​​​​​​​​​​​​ --- ## 📍 Geographic Presence Babylon Tours operates in **major global tourist destinations**, including: - Paris - London - Amsterdam - Berlin - Rome - New York - Chicago - Los Angeles These multi-city operations make it a **globally distributed tour provider** rather than a single-location agency. ​​​​​​​​​​​​​​​​​​​ --- ## ⭐ Business Model & Positioning - Focuses on **high-quality, curated experiences** rather than mass tourism - Targets travelers seeking **premium, educational, and immersive tours** - Known for **“skip-the-line” access** and efficient itineraries - Often ranks highly on travel platforms like TripAdvisor (top-tier category positions) ​​​​​​​​​​​​​​​​​​​ --- ## 💼 Scale & Financials (Estimates) - Estimated revenue: **$50M–$100M annually** ​​​​​​​​​​​​​​​​​​​ - Operates across **multiple continents** with centralized coordination - Uses a **lean operational model** with local expert guides in each city ​​​​​​​​​​​​​​​​​​​ --- ## 🧭 Key Differentiators - **Expert local guides** with deep subject knowledge - **Interactive storytelling approach** rather than scripted tours - **Small-group / semi-private format** (more intimate than large tours) - Strong emphasis on **customer experience and flexibility** --- ## 🧑​💼 Leadership - Founder & CEO: **Arnaud Azoulay** ​​​​​​​​​​​​​​​​​​​ --- ## 🏁 Summary Babylon Tours is a **well-established, mid-sized global tour operator** known for delivering **high-end, small-group cultural tours** in major cities. Its competitive advantage lies in **personalized experiences, expert guides, and efficient access to major attractions**, positioning it strongly in the premium segment of the tourism market. --- If you want, I can break down their competitors, pricing strategy, or whether they’re a good company to book with. | E36: chatgpt/default | F36: US | G36: 1 | H36: Babylon Tours
A37: ch_f32a0726-cd90-4b0c-b7db-f06e362845a3 | B37: chatgpt/default | C37: Babylon Tours company overview | D37: Here’s a thorough overview of a hypothetical company called **Babylon Tours**. I’ll structure it as a professional company profile: --- ### **Babylon Tours – Company Overview** **Company Name:** Babylon Tours **Industry:** Travel & Tourism **Founded:** [Insert Year] **Headquarters:** [City, Country] **Website:** [Insert URL] #### **About Us** Babylon Tours is a premier travel and tourism company specializing in immersive cultural, historical, and adventure experiences around the world. Our mission is to connect travelers with authentic experiences while providing high-quality service and memorable journeys. #### **Vision** To be recognized as a leading provider of transformative travel experiences that inspire curiosity, learning, and connection with global cultures. #### **Mission** - Deliver unique, safe, and enjoyable travel experiences for all types of travelers. - Foster sustainable tourism practices that respect local communities and environments. - Provide personalized services, ensuring each trip exceeds expectations. #### **Core Services** 1. **Guided Cultural Tours:** Explore historical sites, museums, and cultural landmarks with expert guides. 2. **Adventure Travel:** Trekking, hiking, safaris, and extreme sports for thrill-seekers. 3. **Customized Itineraries:** Tailor-made trips to meet the specific needs of individuals, families, or corporate groups. 4. **Luxury Travel Experiences:** High-end accommodations, private tours, and exclusive experiences. 5. **Educational Tours:** Programs for students and academic groups focusing on history, art, and culture. #### **Key Strengths** - Experienced and multilingual tour guides. - Strong partnerships with hotels, airlines, and local service providers. - Commitment to sustainable and responsible tourism. - High customer satisfaction and repeat client rate. #### **Target Market** - Leisure travelers seeking cultural immersion. - Adventure and sports enthusiasts. - Educational institutions planning field trips. - Corporate clients seeking team-building retreats. #### **Social Responsibility** Babylon Tours actively supports local communities through employment, fair-trade partnerships, and initiatives that preserve cultural heritage and natural environments. #### **Contact Information** - **Email:** info@babylontours.com - **Phone:** +[Country Code] [Phone Number] - **Address:** [Insert Address] --- If you want, I can also create a **short, punchy marketing version** suitable for brochures or investor presentations that highlights the brand’s uniqueness and appeal. Do you want me to do that next? | E37: chatgpt/default | F37: US | G37: 1 | H37: Babylon Tours
... A39: ch_7c761626-2b17-4e35-b309-f19c93382d56 | B39: chatgpt/default | C39: Babylon Tours company overview | D39: Babylon Tours is a travel and tourism company that offers guided tours, private experiences, and other travel-related services primarily focused on providing immersive, high-quality experiences to travelers. They typically specialize in destinations with rich historical and cultural significance, offering unique insights into the places they visit. Here’s an overview of their general services: ### 1. **Guided Tours** Babylon Tours is known for its expert-guided tours. Their guides are often well-versed in history, art, culture, and local traditions, allowing travelers to explore destinations with an in-depth understanding. The tours are often private, offering a more personalized experience. ### 2. **Destinations** The company focuses on a variety of iconic, culturally rich, and historically significant destinations. This may include places like: - **Egypt** (e.g., Cairo, Giza Pyramids, Luxor) - **Israel** (e.g., Jerusalem, Tel Aviv, the Dead Sea) - **Jordan** (e.g., Petra, Wadi Rum) - **Turkey** (e.g., Istanbul, Ephesus, Cappadocia) Babylon Tours often operates in regions with ancient civilizations, making it a good choice for travelers interested in history and archaeology. ### 3. **Private Tours** Babylon Tours offers private tours, which allow guests to customize their itinerary, schedule, and even the type of transportation. This makes the experience more flexible and tailored to individual preferences. ### 4. **Expert Guides** The company prides itself on its professional guides, who are experts in their fields. These guides offer personalized attention and are trained to make the travel experience informative and enjoyable. ### 5. **Customizable Experiences** Babylon Tours allows clients to design their own travel experiences. Whether it's a multi-day excursion or a one-day exploration, travelers can adjust the tour to their own interests, be it food, history, art, or adventure. ### 6. **Cultural and Historical Focus** The company places a strong emphasis on culture, history, and unique local experiences. Their tours often include visits to archaeological sites, cultural performances, and even local dining experiences to help travelers immerse themselves fully in the destination. ### 7. **Travel Services** In addition to tours, Babylon Tours may offer other services such as transportation (e.g., private drivers), hotel bookings, and other logistical support to make the entire travel experience seamless. ### 8. **Customer Satisfaction** Many travelers who book with Babylon Tours report high levels of satisfaction, particularly with the knowledge and friendliness of the tour guides. The company often receives positive reviews for its ability to offer enriching experiences while maintaining comfort and convenience. If you have a specific question or destination in mind related to Babylon Tours, feel free to ask! | E39: chatgpt/default | F39: US | G39: 1 | H39: Babylon Tours
A40: ch_a378a59f-1621-5db2-95d1-343babc86e9d | B40: chatgpt/default | C40: Top Paris museum tours | D40: ​​​​​ Here are some of the **top museum tours and experiences you can book in Paris** — perfect for first​time visitors or art lovers wanting guided insights and skip​the​line access: ​​​​​​​​​​​​​​​​​​​​​​​​​​​​​​​​ ### 🎨 Iconic Museum Tours **Louvre & Major Masterpieces** - Guided tours of **Louvre Museum​​​​​​​​​​​​​​​​​​​​​​​​​​​​​​​​** highlight world​famous works like the **Mona Lisa** and **Venus de Milo**, with skip​the​line access and expert commentary. ​​​​​​​​​​​​​​​​​​​ - Options include **small group**, **VIP**, **private**, and even **after​hours** tours. ​​​​​​​​​​​​​​​​​​​​​​​​​​​​​​​​ **Musée d’Orsay Experience** - Book a **guided Impressionist tour** at **Musée d'Orsay​​​​​​​​​​​​​​​​​​​​​​​​​​​​​​​​**, famed for works by Monet, Van Gogh and Renoir — with skip​the​line and expert explanation. ​​​​​​​​​​​​​​​​​​​​​​​​​​​​​​​​​ ### 🖼️ Other Great Museum Tours - **Private or family tours** of various museums, art movements, and periods from **Paris Muse | Private & Family Tours​​​​​​​​​​​​​​​​​​​​​​​​​​​​​​​​** — tailored experiences that go beyond the basics. ​​​​​​​​​​​​​​​​​​​ - Tours often include visits to museums like **Musée Rodin​​​​​​​​​​​​​​​​​​​​​​​​​​​​​​​​**, **Musée de l'Orangerie​​​​​​​​​​​​​​​​​​​​​​​​​​​​​​​​​** (Monet’s Water Lilies), or lesser​known gems like Islamic art, medieval art, and specialty collections. ​​​​​​​​​​​​​​​​​​​​​​​​​​​​​​​​​ ### 📌 Tips for Booking - Look for **skip​the​line tickets** to avoid queues at major museums — especially at the Louvre. ​​​​​​​​​​​​​​​​​​​ - Many tours combine museums with walking tours, wine tastings, or historic neighborhood explorations. ​​​​​​​​​​​​​​​​​​​ - You can also choose **private guides** if you prefer a personalized art and history experience. ​​​​​​​​​​​​​​​​​​​ Would you like *specific tour recommendations* with prices and durations for the Louvre and Orsay? | E40: chatgpt/default | F40: US | G40: -
A41: ch_4fc425a8-278a-5380-8804-37b145415ce2 | B41: chatgpt/default | C41: Top Paris museum tours | D41: Paris is a treasure trove of world-class museums, and there are plenty of amazing tours that can take you through some of the most iconic ones. Here are some of the top museum tours in Paris: ### 1. **Louvre Museum Tour** - **Why it’s amazing**: The Louvre is the world’s largest and most visited museum. It’s home to thousands of works of art, including the *Mona Lisa*, *Venus de Milo*, and *Winged Victory of Samothrace*. Guided tours can help you navigate the vast collections, focusing on specific themes, periods, or famous masterpieces. - **Tour options**: You can join a general tour or opt for thematic tours like "Masterpieces of the Louvre" or "Greek Antiquities." - **Best for**: Art lovers and history buffs. ### 2. **Musée d'Orsay Tour** - **Why it’s amazing**: Housed in a former railway station, Musée d'Orsay boasts an impressive collection of Impressionist and Post-Impressionist masterpieces, including works by Monet, Van Gogh, Degas, and Renoir. - **Tour options**: Skip-the-line tours, private tours, and special themed tours such as "Impressionism in Paris" or "The Rise of Modern Art." - **Best for**: Fans of Impressionist and modern art. ### 3. **Centre Pompidou (Beaubourg) Tour** - **Why it’s amazing**: Known for its unique architectural style, the Centre Pompidou is a hub of modern and contemporary art. It features works from artists like Picasso, Kandinsky, and Duchamp. - **Tour options**: A guide can walk you through the key collections or focus on contemporary art movements like Dadaism, Surrealism, or Abstract Expressionism. - **Best for**: Contemporary art lovers and architecture enthusiasts. ### 4. **Musée de l'Orangerie Tour** - **Why it’s amazing**: This smaller museum is renowned for its stunning display of Monet’s *Water Lilies* and its collection of works by Renoir, Matisse, and Cézanne. - **Tour options**: A guided tour of the *Water Lilies* and other impressionist pieces, or a thematic tour on Monet’s influence. - **Best for**: Fans of Impressionist art and more intimate museum experiences. ### 5. **Musée Rodin Tour** - **Why it’s amazing**: This museum is dedicated to the works of sculptor Auguste Rodin, featuring pieces like *The Thinker* and *The Kiss*. The beautiful garden setting adds an extra layer of charm. - **Tour options**: Garden tours, guided tours of Rodin's most famous sculptures, and private tours focused on his life and works. - **Best for**: Sculpture enthusiasts and lovers of outdoor art experiences. ### 6. **Musée Picasso Paris Tour** - **Why it’s amazing**: The Picasso Museum houses an extensive collection of the artist’s works, showcasing his evolution from his Blue Period to his later abstract works. - **Tour options**: A detailed tour exploring Picasso’s life and artistic phases, or a more general overview of 20th-century art in Paris. - **Best for**: Fans of Picasso and modern art. ### 7. **Musée Carnavalet Tour (Museum of the History of Paris)** - **Why it’s amazing**: This museum tells the story of Paris, with a focus on the French Revolution. You’ll see artifacts, paintings, and items that bring the history of the city to life. - **Tour options**: A historical tour focusing on the French Revolution, or a general Paris history tour. - **Best for**: History enthusiasts and those interested in the evolution of Paris. ### 8. **Musée Jacquemart-André Tour** - **Why it’s amazing**: A stunning 19th-century mansion turned museum, this museum houses a rich collection of fine art, including works by Italian Renaissance masters and French Rococo artists. - **Tour options**: Guided tours that focus on the mansion’s architecture, art collections, or specific periods in French history. - **Best for**: Those who love a mix of art, history, and opulent interiors. ### 9. **The Musée du Quai Branly – Jacques Chirac Tour** - **Why it’s amazing**: This museum focuses on non-Western art, with incredible collections of African, Asian, Oceanic, and Native American art. The building itself, designed by Jean Nouvel, is a modern architectural marvel. - **Tour options**: Thematic tours on African art, indigenous cultures, or specific art objects. - **Best for**: Those interested in world cultures and non-Western art traditions. ### 10. **Musée Cluny – Musée National du Moyen Âge Tour** - **Why it’s amazing**: This medieval museum, housed in a former abbey, is home to the famous *Lady and the Unicorn* tapestries and a wealth of medieval artifacts. - **Tour options**: Tours on medieval life, art, and architecture, with a focus on the museum’s unique pieces. - **Best for**: Fans of the Middle Ages, history buffs, and textile art enthusiasts. --- ### Tour Tips: - **Skip-the-line tickets**: For popular museums like the Louvre, it’s a good idea to book skip-the-line tickets in advance to avoid long waits. - **Private tours**: Many museums offer private guides, which can give you a more personalized experience. - **Audio guides**: Most major museums have audio guides available in multiple languages, which are a great alternative if you prefer exploring on your own but still want context. Would you like any more details on one of these museums or a specific tour? | E41: chatgpt/default | F41: US | G41: -
A42: ch_ce939db1-8658-5d5f-8219-7c81edc0e3e7 | B42: chatgpt/default | C42: Top Paris museum tours | D42: Here are some of the **top Paris museum tours**—especially the ones travelers consistently rate highest for saving time and actually understanding what you’re seeing (instead of wandering aimlessly through massive galleries). --- # 🏛️ Best Paris Museum Tours (2026) ## 1. Louvre Museum​​​​​​​​​​​​​​​​​​​​​​​​​​​​​​​​​​​​​​​​​​​​​​​​​ – Skip-the-Line & Masterpieces Tours **⭐ Best overall museum tour in Paris** **Top options:** - *Louvre Masterpieces Skip-the-Line Tour* - *Semi-private (small group) Louvre tour* - *Closing-time Louvre tour (less crowded)* **Why it’s worth it:** - Fast-track entry saves **hours of waiting** ​​​​​​​​​​​​​​​​​​​ - Expert guides take you directly to highlights like the Mona Lisa - Smart routes help you navigate the world’s largest museum efficiently ​​​​​​​​​​​​​​​​​​​ **Typical duration:** 2–3 hours **Best for:** First-time visitors 👉 Tip: Small-group tours (6–10 people) are widely considered the best experience. --- ## 2. Musée d'Orsay​​​​​​​​​​​​​​​​​​​​​​​​​​​​​​​​​​​​​​​​​​​​​​​​​ – Impressionist Art Tours **🎨 Best for art lovers (Van Gogh, Monet, Degas)** **Top option:** - *Impressionist Highlights Guided Tour* **Why it’s great:** - Focuses on Impressionism—the most “approachable” art movement - Guides explain context and stories behind famous works - Much easier to digest than the Louvre **Typical duration:** 1.5–2 hours **Best for:** People who want depth without overwhelm 👉 Often ranked as one of the most enjoyable museum tours in Paris ​​​​​​​​​​​​​​​​​​​ --- ## 3. Palace of Versailles​​​​​​​​​​​​​​​​​​​​​​​​​​​​​​​​​​​​​​​​​​​​​​​​​​​​​​ – Palace + Museum Tour **👑 Best day-trip museum experience** **Top options:** - *Skip-the-line Versailles Palace tour* - *Versailles + Gardens guided tour* **Why it stands out:** - Combines art, history, and architecture - Skip-the-line access is crucial (lines can be long) ​​​​​​​​​​​​​​​​​​​ - Guides explain royal life, which adds huge value **Typical duration:** Half-day to full day **Best for:** History + architecture fans --- ## 4. Centre Pompidou​​​​​​​​​​​​​​​​​​​​​​​​​​​​​​​​​​​​​​​​​​​​​​​​​ – Modern Art Tours **🧠 Best for contemporary & modern art** **Why go:** - Covers Picasso, Kandinsky, Duchamp - Guides help decode abstract and modern works - Less crowded than major museums **Typical duration:** 1.5–2 hours **Best for:** Modern art curiosity (or confusion 😄) --- ## 5. Musée de l'Orangerie​​​​​​​​​​​​​​​​​​​​​​​​​​​​​​​​​​​​​​​​​​​​​​​​​ – Monet Water Lilies Tour **🌿 Best short, peaceful museum tour** **Highlights:** - Monet’s immersive Water Lilies rooms - Quick but powerful experience **Typical duration:** ~1 hour **Best for:** Short visits or relaxed itinerary days --- ## 6. Combo Tours (Great Value) **🔥 Best if you’re short on time** Popular combo: - Louvre + Eiffel Tower + Notre-Dame in one day **Why choose this:** - Efficient itinerary planning - Often includes skip-the-line access everywhere - Great for first-time Paris trips --- # 💡 How to Choose the Right Tour **Go for Louvre if:** - It’s your first time in Paris - You want the “must-see” experience **Pick Musée d’Orsay if:** - You prefer a calmer, more focused museum **Choose Versailles if:** - You want a big, memorable half/full-day experience **Always prioritize:** - **Skip-the-line access** (huge time saver) - **Small group size** (better experience) - **Expert guides** (makes art actually interesting) --- # 🧭 Quick Recommendation - **Best overall:** Louvre small-group skip-the-line tour - **Best art experience:** Musée d’Orsay Impressionist tour - **Best day trip:** Versailles guided tour --- If you want, tell me your travel style (budget, first time vs repeat, how many days), and I’ll recommend **specific tours you can book** that fit perfectly. | E42: chatgpt/default | F42: US | G42: -
A43: ch_b606ab3c-b0bf-550a-a977-3079807b3d3b | B43: chatgpt/default | C43: Top Paris museum tours | D43: Here are some of the **top-rated Paris museum tours**—from quick highlights to deep, expert-led experiences—so you can pick what fits your style and time. --- # 🎨 Best Paris Museum Tours ## 🏛️ 1. Louvre skip-the-line & highlights tours - **“Secrets of the Louvre” / Highlights Tour (2–3 hrs)** - Focus: Mona Lisa, Venus de Milo, major masterpieces - Why it’s great: You skip huge lines and get context fast - Typical price: ~$75–$120 👉 These tours are consistently ranked among the best because the Louvre is विशाल (35,000+ works), and a guide helps you avoid getting lost and focus on key pieces. ​​​​​​​​​​​​​​​​​​​​​​​​​​​​​​​​ **Best for:** First-time visitors, limited time --- ## 🎧 2. Semi-private Louvre tours (small groups) - Small groups (6–8 people) - More interaction with your guide - Often includes headsets + deeper storytelling 👉 You’ll get a more personal experience and can ask questions—ideal if you actually want to understand the art, not just see it. ​​​​​​​​​​​​​​​​​​​ **Best for:** Art lovers, couples, quieter experience --- ## 🖼️ 3. Musée d’Orsay Impressionist tours - Focus on Monet, Van Gogh, Renoir, Degas - Usually 2–3 hours with skip-the-line access 👉 These are highly rated because the Orsay is more manageable and the storytelling around Impressionism really enhances the visit. ​​​​​​​​​​​​​​​​​​​ **Best for:** Impressionism fans, relaxed pace --- ## 🔥 4. Combo tour: Louvre + Orsay (same day) - 4–6 hours total - Guided highlights in both museums - Skip-the-line access included 👉 One of the **best value tours**—you cover two of Paris’s top museums efficiently with expert guidance. ​​​​​​​​​​​​​​​​​​​​​​​​​​​​​​​​ **Best for:** Short trips, “see it all” travelers --- ## 👑 5. Private Paris museum tours (VIP experience) - Fully customizable itinerary - Personal guide - Often includes hotel pickup 👉 These tours give you the deepest experience and flexibility—great if you want to go beyond the basics. ​​​​​​​​​​​​​​​​​​​ **Best for:** Luxury travelers, serious art enthusiasts --- ## 🗼 6. Full-day Paris culture tours (museum + landmarks) - Combines museums + sites like Eiffel Tower or Notre Dame - ~6–7 hours 👉 Ideal if you want a guided overview of Paris, not just museums. ​​​​​​​​​​​​​​​​​​​ **Best for:** First-time visitors wanting a full city intro --- # 💡 Tips Before You Book - **Always choose skip-the-line** (lines can be hours long) - **Morning or evening tours** = fewer crowds - **Small groups or private tours** = better experience - Consider a **Paris Museum Pass** if visiting multiple sites ​​​​​​​​​​​​​​​​​​​ --- # 👍 Quick Recommendations - **Best overall:** Louvre skip-the-line highlights - **Best combo:** Louvre + Orsay small-group tour - **Best value:** Semi-private tour - **Best deep dive:** Private guide --- If you tell me: - how many days you have - budget - whether you love art or just want highlights …I can suggest the *exact* tour (with links and ideal itinerary). | E43: chatgpt/default | F43: US | G43: -
A44: ch_bed91c0e-8bd0-4d1f-b1fd-c21a44baf36e | B44: chatgpt/default | C44: Top Paris museum tours | D44: Here are some of the **top​rated museum tours and experiences in Paris** — perfect if you want deeper insight from expert guides, skip long lines, and make the most of your time in the City of Light: ​​​​​​​​​​​​​​​​​​​​​​​​​​​​​​​​​​​​​​​​​​​​​ ### 🎨 **1. Louvre Museum Guided Tours** - *VIP & skip​the​line tours* that focus on major works like the **Mona Lisa** and **Venus de Milo**, often with expert commentary. ​​​​​​​​​​​​​​​​​​​ - Semi​private and small​group tours lasting ~2–3 hrs are very popular. ​​​​​​​​​​​​​​​​​​​ - Many companies offer combinations of Louvre highlights with other Paris sites (e.g., Eiffel Tower). ​​​​​​​​​​​​​​​​​​​ ### 🖼️ **2. Musée d’Orsay Guided Tour** - Tours here focus on *Impressionist and Post​Impressionist masterpieces* by Monet, Renoir, Van Gogh and more. ​​​​​​​​​​​​​​​​​​​​​​​​​​​​​​​​​ - Typically ~2 hrs with skip​the​line access available. ​​​​​​​​​​​​​​​​​​​​ ### 🗿 **3. Musée Rodin Tours** - Guided and private tours of *Musée Rodin* explore works by Auguste Rodin in the garden and galleries. ​​​​​​​​​​​​​​​​​​​ - Options include small English​speaking group tours or private experiences. ​​​​​​​​​​​​​​​​​​​ ### 🖌️ **4. Museum Combo & Themed Tours** - Some tour providers bundle several top museums (e.g., Louvre + Orsay + Orangerie). ​​​​​​​​​​​​​​​​​​​​ - The *Paris Museum Pass* lets you access **60+ museums and monuments** with one card (ideal if you’re planning multiple visits). ​​​​​​​​​​​​​​​​​​​​ ### 🧑​🏫 **5. Specialized & Private Guides** - Local guides and companies like *Take Walks* offer **skip​the​line experiences** and *after​hours or themed tours* that go beyond standard visits. ​​​​​​​​​​​​​​​​​​​ - Private or customized tours of museums like Louvre, Orsay, Centre Pompidou, Picasso Museum, etc., are also widely available. ​​​​​​​​​​​​​​​​​​​ --- ### 🏛️ **Quick Tips for Museum Tours in Paris** - **Book ahead:** For top museums like the Louvre and Orsay, advance reservations (especially for guided tours) help skip queues. ​​​​​​​​​​​​​​​​​​​​ - **Consider a museum pass:** Even if you don’t use it for guided tours, it often gives priority entry and savings on multiple entries. ​​​​​​​​​​​​​​​​​​​​ - **Choose the style:** Audio guides, private tours, or semi​private groups all offer different experiences depending on your interests and pace. ​​​​​​​​​​​​​​​​​​​ --- Would you like **specific tour recommendations with prices and booking links** (e.g., Louvre, Orsay, Rodin)? That can help you plan exact days and costs. | E44: chatgpt/default | F44: US | G44: -
A45: ch_520d8590-04d1-4ccb-99a6-4db7bbefa2c5 | B45: chatgpt/default | C45: Top Paris museum tours | D45: Paris is packed with amazing museums, and the tours you can take will definitely enrich your experience. Here are some of the top museum tours you can check out: ### 1. **Louvre Museum** **Tour Type**: Guided or Audio Guide - **Highlights**: Mona Lisa, Venus de Milo, The Winged Victory of Samothrace - **Why Go**: The Louvre is the world’s largest museum and is home to thousands of works of art spanning thousands of years. A guided tour will help you navigate its vastness, focusing on the most famous pieces or themed tours, like Ancient Egypt or Renaissance art. - **Tip**: Consider a skip-the-line tour to avoid long waits. ### 2. **Musée d'Orsay** **Tour Type**: Guided or Audio Guide - **Highlights**: Van Gogh, Monet, Degas, and other Impressionist works - **Why Go**: Housed in a former railway station, this museum focuses on art from 1848 to 1914, with an emphasis on French artists. The building itself is stunning, and a tour here will help you understand the transition from classical to modern art. - **Tip**: Try a tour that includes both Musée d'Orsay and the nearby Musée de l'Orangerie for a full Impressionist experience. ### 3. **Centre Pompidou** **Tour Type**: Guided Tour - **Highlights**: Modern and contemporary art from artists like Kandinsky, Picasso, and Duchamp - **Why Go**: This museum is known for its radical architecture (the pipes on the outside of the building) and its collection of 20th- and 21st-century art. It’s a great spot for modern art lovers, and the views from the rooftop are fantastic. - **Tip**: Consider a private tour if you’re particularly interested in modern art history. ### 4. **Musée Rodin** **Tour Type**: Guided Tour - **Highlights**: The Thinker, The Gates of Hell, and Rodin’s sculptures - **Why Go**: If you love sculpture, this museum is a must-see. It’s housed in the former home of the artist, and the garden is also home to some of his most iconic works. - **Tip**: Don’t miss the beautiful garden, which is perfect for a peaceful stroll. ### 5. **Musée de l'Orangerie** **Tour Type**: Self-Guided with an Audio Guide or Guided - **Highlights**: Monet’s Water Lilies, works by Cézanne, Matisse, and Renoir - **Why Go**: A smaller museum, but it holds an incredible collection of Impressionist and post-Impressionist works. Monet's huge Water Lilies murals are the museum’s crown jewel. - **Tip**: If you're short on time but want to see something amazing, this museum is ideal for a quick but enriching visit. ### 6. **Musée Carnavalet** **Tour Type**: Guided Tour - **Highlights**: History of Paris, from the French Revolution to the 20th century - **Why Go**: Located in the historic Marais district, this museum is dedicated to the history of Paris. It’s a fascinating place to learn about the French Revolution and how Paris evolved over the centuries. - **Tip**: A guided tour will help you navigate the vast history presented here, especially the Revolution exhibits. ### 7. **Musée Jacquemart-André** **Tour Type**: Self-Guided with an Audio Guide or Guided Tour - **Highlights**: Private collection of French and Italian art - **Why Go**: This is a lesser-known gem in Paris. It’s a former private mansion turned museum, showcasing an incredible collection of art, furniture, and sculptures from the 18th and 19th centuries. - **Tip**: Take your time here as the museum is less crowded, giving you a more intimate experience. ### 8. **Musée Quai Branly – Jacques Chirac** **Tour Type**: Guided Tour - **Highlights**: Art and artifacts from Africa, Asia, Oceania, and the Americas - **Why Go**: This museum offers a deep dive into non-Western cultures and their art. The modern architecture is also fascinating, and a tour will guide you through the different cultural exhibitions. - **Tip**: Don’t miss the incredible garden and the outdoor space next to the Seine. ### 9. **Musée Picasso** **Tour Type**: Guided or Audio Guide - **Highlights**: Picasso’s paintings, sculptures, sketches, and personal items - **Why Go**: The Musée Picasso houses an impressive collection of the artist’s work, spanning his entire career. It also provides insight into his life and influences, making it a great stop for Picasso fans. - **Tip**: Combine this museum with a visit to the nearby Marais district, which is charming to explore on foot. ### 10. **Musée de Cluny - Musée National du Moyen Âge** **Tour Type**: Self-Guided with Audio Guide - **Highlights**: The Lady and the Unicorn tapestries, medieval art and artifacts - **Why Go**: If you’re interested in medieval history, this is the place to go. It’s housed in a medieval mansion and is a fantastic stop to learn more about the Middle Ages in France. - **Tip**: The tapestries in the museum are a must-see, and the museum’s setting makes for a special visit. ### General Tips: - **Book in advance**: Many museums offer skip-the-line tickets for guided tours, which can save you time. - **Check museum schedules**: Some museums have seasonal hours or temporary exhibitions that are worth knowing about before your visit. - **Combo Tours**: Some companies offer combo tours where you can visit multiple museums in one day. This can be a good way to get the most out of your time in Paris. Let me know if you’d like more specific info on one of these! | E45: chatgpt/default | F45: US | G45: -
A46: ch_02b0093e-8030-4afc-91cf-f6756ada8fd3 | B46: chatgpt/default | C46: Top Paris museum tours | D46: ​​​​​ Here are some great **top museum tours and ways to explore museums in Paris** — from must​see classics to expert​guided experiences: ### 🎨 Iconic Museum Tours **1. Louvre Museum​​​​​​​​​​​​​​​​​​​​​​​​​​​​​​​​ Tours** - Skip​the​line guided tours focusing on highlights like the *Mona Lisa*, *Venus de Milo*, and *Winged Victory*. ​​​​​​​​​​​​​​​​​​​ - Options include standard group tours, semi​private tours, and visits at closing time. ​​​​​​​​​​​​​​​​​​​ **2. Musée d'Orsay​​​​​​​​​​​​​​​​​​​​​​​​​​​​​​​​ Guided Visits** - Expert tours that focus on Impressionist and Post​Impressionist art (Monet, Renoir, Van Gogh). ​​​​​​​​​​​​​​​​​​​ - Semi​private, skip​the​line options available. ​​​​​​​​​​​​​​​​​​​ **3. Combined Louvre + Orsay Tours** - Half​day or full​day combined experiences covering both major art museums with a professional guide. ​​​​​​​​​​​​​​​​​​​​​​​​​​​​​​​​​ ### 🗺️ Guided Tour Providers in Paris Professional companies that organize museum tours and cultural visits: - **Paris Muse | Private & Family Tours​​​​​​​​​​​​​​​​​​​​​​​​​​​​​​​​** – Highly rated for personalized and family​friendly tours. - **Babylon Tours Paris​​​​​​​​​​​​​​​​​​​​​​​​​​​​​​​​** – Excellent skip​the​line museum and city tours. - **Paris City Vision​​​​​​​​​​​​​​​​​​​​​​​​​​​​​​​​** – Large​scale guided tours including museum options. - **Discover Walks​​​​​​​​​​​​​​​​​​​​​​​​​​​​​​​​** – Small​group city tours that can include museum highlights. - **Explore Paris Tours​​​​​​​​​​​​​​​​​​​​​​​​​​​​​​​​​** – Boutique guided experiences. - **Best of France Tours​​​​​​​​​​​​​​​​​​​​​​​​​​​​​​​​** – Top​rated local guide service for cultural tours. ### 🖼️ Other Museums & Tour Ideas Paris has many other cultural gems worth touring: - **Musée de l'Orangerie​​​​​​​​​​​​​​​​​​​​​​​​​​​​​​​​** – Famous for Monet’s *Water Lilies*. - **Musée Rodin​​​​​​​​​​​​​​​​​​​​​​​​​​​​​​​​** – Sculpture museum with lovely gardens. - Combining tours with passes like the Paris Museum Pass lets you visit multiple venues at your own pace. ​​​​​​​​​​​​​​​​​​​ --- If you want, I can share specific tour options with prices and booking links! | E46: chatgpt/default | F46: US | G46: 1 | H46: Babylon Tours
A47: ch_295816dc-df9d-5421-9e56-4a9a5f1ab810 | B47: chatgpt/default | C47: What is Babylon Tours known for? | D47: Could you clarify which "Babylon Tours" you mean? Are you referring to a **travel company**, a **historical/cultural tour operator**, or something else? There may be several entities with that name. Once I know which one, I can give a detailed explanation of what they’re known for. | E47: chatgpt/default | F47: US | G47: 1 | H47: Babylon Tours
A48: ch_ce35b446-497a-5d90-9315-ae8c9492be28 | B48: chatgpt/default | C48: What is Babylon Tours known for? | D48: **Babylon Tours** is best known as a **global travel company that offers guided cultural tours**, especially focused on art, history, and major attractions in big cities. Here’s what they’re particularly known for: ### 1. Private and small-group guided tours They specialize in **intimate, high-quality tours** rather than large crowds—often private or small groups led by expert guides. ​​​​​​​​​​​​​​​​​​​ ### 2. Museum and walking tours Their core offerings are: - **Museum tours** (like famous art museums) - **City walking tours** exploring history, landmarks, and neighborhoods ​​​​​​​​​​​​​​​​​​​​ ### 3. Skip-the-line access A major selling point is **priority entry to popular attractions**, helping travelers avoid long waits at places like major museums. ​​​​​​​​​​​​​​​​​​​ ### 4. Focus on art, history, and culture Their tours are designed to be **educational and immersive**, with guides explaining: - Art and artists - Historical context - Cultural significance of landmarks ​​​​​​​​​​​​​​​​​​​ ### 5. Top-rated experiences in major cities They operate in cities like Paris, Rome, London, and New York, and are often **highly rated on travel platforms**, frequently ranking among the top tour providers in those locations. ​​​​​​​​​​​​​​​​​​​ ### 6. Signature tours (especially the Louvre) They’re especially famous for their **guided tours of the Louvre Museum**, which have won top travel awards and recognition. ​​​​​​​​​​​​​​​​​​​ --- **In short:** Babylon Tours is known for **premium, guided cultural experiences—especially museum tours with expert guides and skip-the-line access in major world cities.** If you want, I can tell you whether they’re worth it compared to other tour companies or what their tours are like in a specific city. | E48: chatgpt/default | F48: US | G48: 1 | H48: Babylon Tours
A49: ch_007056c0-2077-5a37-ad79-a2e65b45a42c | B49: chatgpt/default | C49: What is Babylon Tours known for? | D49: Could you clarify which “Babylon Tours” you mean? Are you asking about a travel company, a historical reference, or something else? There are multiple entities and contexts where “Babylon Tours” could come up. This will help me give a precise answer. | E49: chatgpt/default | F49: US | G49: 1 | H49: Babylon Tours
A50: ch_edc2c73e-ddc2-5e0c-b64d-ac0f3cdffe84 | B50: chatgpt/default | C50: What is Babylon Tours known for? | D50: **Babylon Tours** (Babylon Tours​​​​​​​​​​​​​​​​​​​​​​​​​​​​​​​​​​​​​​​​​​​​​​) is mainly known for offering **high-quality guided travel experiences**, especially focused on culture, art, and history. Here’s what they’re best known for: ### 🏛️ 1. Private museum and walking tours They specialize in **small-group and private guided tours** of major attractions—especially famous museums and landmarks in cities like Paris, Rome, and New York. ​​​​​​​​​​​​​​​​​​​​​​​​​​​​​​​​ ### ⏱️ 2. “Skip-the-line” access A big selling point is **priority entry to popular sites**, helping travelers avoid long waits at places like the Louvre or Vatican Museums. ​​​​​​​​​​​​​​​​​​​ ### 🎓 3. Expert local guides Their tours are led by **knowledgeable, hand-picked guides** who focus on storytelling and making history and art engaging and easy to understand. ​​​​​​​​​​​​​​​​​​​ ### 🌍 4. Tours in major global cities They operate in many top destinations across Europe and the U.S., offering curated experiences in cities such as Paris, London, Amsterdam, and Washington, D.C. ​​​​​​​​​​​​​​​​​​​ ### ⭐ 5. Strong reputation and ratings Babylon Tours is widely recognized as a **top-rated tour operator**, often ranking highly on travel platforms and even earning “Best of the Best” awards for certain experiences. ​​​​​​​​​​​​​​​​​​​ --- **In short:** Babylon Tours is known for **premium, small-group cultural tours with expert guides and fast-track access to major attractions**, designed to give travelers a deeper and more personal experience. If you want, I can compare them to other tour companies or tell you whether they’re worth it for a specific city. | E50: chatgpt/default | F50: US | G50: 1 | H50: Babylon Tours
A51: ch_e61ff938-a117-4a44-85dc-1f96a798e18b | B51: chatgpt/default | C51: What is Babylon Tours known for? | D51: Could you clarify which “Babylon Tours” you mean? There are a few possibilities: 1. **Historical/archaeological tours in Iraq** around the ancient city of Babylon, which is famous for its ruins, the Hanging Gardens (one of the Seven Wonders of the Ancient World), and the Tower of Babel legend. 2. A **tour company named “Babylon Tours”** in a particular country that organizes travel or sightseeing trips. If you mean the historical/archaeological context, Babylon Tours would be known for offering guided visits to **ancient Mesopotamian sites**, highlighting **ruins, inscriptions, ziggurats, and cultural history**. If you’re asking about a commercial tour operator, I can give specifics if you tell me the country or city. Which one do you mean? | E51: chatgpt/default | F51: US | G51: 1 | H51: Babylon Tours
A52: ch_83b29797-5b57-4afb-a203-12cdd29e6f4b | B52: chatgpt/default | C52: What is Babylon Tours known for? | D52: Babylon Tours is a **travel and tour operator** best known for its **guided cultural, museum, and walking tours** in major cities around the world — especially in **Paris**. It specializes in **private and small​group tours** that help travelers explore places like the **Louvre Museum**, Musée d’Orsay, historic districts, and other cultural highlights with expert local guides. Their tours are highly rated for providing **insightful storytelling, skip​the​line access, and deep context about art, history, and local culture.** ​​​​​​​​​​​​​​​​​​​​​​​​​​​​​​​​​ | E52: chatgpt/default | F52: US | G52: 1 | H52: Babylon Tours
A53: ch_1e1cfd2a-a62a-44f3-a16e-e949d9e4e5da | B53: chatgpt/default | C53: What is Babylon Tours known for? | D53: **Babylon Tours** is best known as a **global tour operator specializing in high-quality, guided cultural experiences**, especially: ### 🏛️ Private museum tours - Their core focus is **expert-led tours of major museums** (like the Louvre, Vatican Museums, etc.). - Many tours include **“skip-the-line” access**, helping visitors avoid long queues. ​​​​​​​​​​​​​​​​​​​ ### 🚶 Walking tours of major cities - They offer **guided walking tours** in cities like Paris, Rome, London, New York, and more. - These tours blend **history, art, and storytelling** to make destinations more immersive. ​​​​​​​​​​​​​​​​​​​ ### 👥 Small-group and private experiences - Babylon Tours is especially known for **intimate, small-group or private tours**, rather than large crowds. - The emphasis is on **personal attention and interaction with knowledgeable guides**. ​​​​​​​​​​​​​​​​​​​ ### ⭐ Highly rated tour operator - Founded in 2012 in Paris, it has become **one of the top-rated tour companies globally**, often ranking highly on travel platforms. - Some of their tours (like Louvre experiences) have received major awards and top rankings. ​​​​​​​​​​​​​​​​​​​ --- ✅ **In short:** Babylon Tours is known for **premium, expert-guided museum and city tours with a focus on small groups, deep cultural insight, and convenience (like skip-the-line access).** If you want, I can compare it to other tour companies or tell you whether it’s worth booking. | E53: chatgpt/default | F53: US | G53: 1 | H53: Babylon Tours
A54: ch_1a3d7cb5-0017-5009-a35a-a1dbdede06b8 | B54: chatgpt/default | C54: Babylon Tours vs The Tour Guy | D54: Are you looking to compare **Babylon Tours** and **The Tour Guy** in terms of **tours, pricing, reliability, or overall experience**? I can break it down point by point. Here’s a structured comparison based on the usual traveler considerations: --- ### 1. **Tour Offerings** - **Babylon Tours**: Focuses mainly on **historical and cultural tours**, often with smaller, more intimate groups. They tend to emphasize **personalized experiences** in locations like Rome, Pompeii, and Greece. - **The Tour Guy**: Offers a **wider variety of tours**, including major attractions, skip-the-line tickets, and large city tours. More commercialized, sometimes with **bigger group sizes** but very structured itineraries. --- ### 2. **Pricing** - **Babylon Tours**: Generally **mid-range**, sometimes slightly higher due to smaller group sizes and more personalized attention. Value is often in **depth of experience**. - **The Tour Guy**: Offers **competitive pricing**, sometimes cheaper for large groups or standard city tours. They often have promotions and packages. --- ### 3. **Tour Guides** - **Babylon Tours**: Guides are usually **local experts**, passionate about history and culture. They often provide a **more storytelling-based, immersive experience**. - **The Tour Guy**: Guides are trained for **efficiency and large groups**, usually excellent at logistics and keeping a strict schedule. Experience may feel **more standardized**. --- ### 4. **Booking & Convenience** - **Babylon Tours**: Booking is straightforward online, but tours can **sell out faster** due to smaller groups. Flexibility may vary depending on the location. - **The Tour Guy**: Very **user-friendly website**, clear cancellation policies, often **available in multiple cities** with consistent service standards. --- ### 5. **Audience & Experience** - **Babylon Tours**: Best for **travelers who want a deeper, personal experience** of history and culture. - **The Tour Guy**: Best for **first-time visitors, families, or large groups** who want a structured and predictable tour. --- **Bottom line:** - Go with **Babylon Tours** if you value **intimate, expert-led tours** with a storytelling approach. - Go with **The Tour Guy** if you want **convenience, variety, and a solid, well-organized experience** across multiple cities. --- If you want, I can make a **quick side-by-side table comparing Babylon Tours vs The Tour Guy** for **Rome or Paris specifically**, so it’s easier to see at a glance which might suit your trip. Do you want me to do that? | E54: chatgpt/default | F54: US | G54: 1 | H54: Babylon Tours
A55: ch_8edc5e8e-9b1a-5bbe-913c-57aa157ae799 | B55: chatgpt/default | C55: Babylon Tours vs The Tour Guy | D55: Here’s a side​by​side comparison of **​​​​​​​​​​​​​​​​​​​​​​​​​​​​​​​​​​​​​​​​​​​​​​​​​​​​​​​​​​​​​​** and **The Tour Guy** so you can see how they differ as tour companies 👇 --- ## 🧭 Overview ### **Babylon Tours** - Babylon Tours is a **global tour operator** founded in Paris around 2012–2014 and now operates in many major cities worldwide (Paris, London, Amsterdam, New York City, Washington, etc.). ​​​​​​​​​​​​​​​​​​​​​​​​​​​​​​​​ - They’re known for **private museum tours, walking tours, and small​group experiences**. ​​​​​​​​​​​​​​​​​​​ - Often highly rated on *TripAdvisor* (e.g., multiple top positions and “Best of the Best” rankings for their Louvre tours). ​​​​​​​​​​​​​​​​​​​ **Strengths highlights** ✅ Strong *TripAdvisor* ratings and awards ✅ Focus on museum and in​depth cultural tours ✅ Private or semi​private group experiences with smaller sizes ​​​​​​​​​​​​​​​​​​​ **Typical experience/feedback** ⭐ Positive reviews often highlight knowledgeable, enthusiastic guides and detailed explanations, especially in museums and cultural sites. ​​​​​​​​​​​​​​​​​​​​ --- ### **The Tour Guy** - The Tour Guy (often associated with the brand *The Roman Guy* for Italy) is a **large tour provider offering hundreds of tours worldwide**, including skip​the​line access to major sites like the Vatican, Colosseum, and Versailles. ​​​​​​​​​​​​​​​​​​​ - They offer **city tours, full​day experiences, food tours, and transport tours** across Europe and beyond. ​​​​​​​​​​​​​​​​​​​ **Strengths highlights** ✅ Very high ratings on some platforms (Trustpilot shows ~4.8/5 from thousands of reviews). ​​​​​​​​​​​​​​​​​​​ ✅ Wide range of tour types — from history to food and wine and multi​city packages. ​​​​​​​​​​​​​​​​​​​ ✅ Good organization and communication reported by many customers. ​​​​​​​​​​​​​​​​​​​ **Mixed feedback** ⚠️ Some online ratings (e.g., smaller review aggregates) show average scores and mention issues. ​​​​​​​​​​​​​​​​​​​ ⚠️ Independent traveler comments sometimes report problems with communication, refunds, or tour coordination — experiences vary widely. ​​​​​​​​​​​​​​​​​​​ --- ## 🆚 Key Differences | Feature | **Babylon Tours** | **The Tour Guy** | |---------|------------------|------------------| | **Tour Style** | Mostly private & small group museum/walking tours | Mix of group & private tours including full day, city, food, water tours | | **Reputation Source** | Very high TripAdvisor scores, often top ranked tours | High Trustpilot rating; mixed reports on other platforms | | **Expertise Focus** | Deep museum knowledge and art history | Broader travel experiences and cultural tours | | **Size & Scale** | Smaller overall company & more curated experiences | Large operator with many offerings across many destinations | | **Typical Group Size** | Smaller, more personalized | Varies widely — large, small, or semi private depending on tour | | **Common Feedback** | Focus on quality and guide expertise | Praise for guides and organization, but occasional complaints on logistics | --- ## 🧠 Which One Is Better? ✅ **Choose Babylon Tours if:** - You want **small group or private tours**. - Your focus is **museums, art, and deep cultural experiences**. ​​​​​​​​​​​​​​​​​​​​ ✅ **Choose The Tour Guy if:** - You want **lots of tour options in many cities**. - You’re interested in **full​day experiences or skip​the​line access**. ​​​​​​​​​​​​​​​​​​​ 👉 Both are reputable but cover slightly different niches — Babylon leans more **specialized and boutique​style**, while The Tour Guy is **broader and more scalable**. --- If you tell me *which city or site you’re planning to visit*, I can compare specific tours from each company (e.g., Louvre vs Vatican) to help you choose! | E55: chatgpt/default | F55: US | G55: 1 | H55: Babylon Tours
A56: ch_910103d1-e091-5269-b1fd-b493c7273ed0 | B56: chatgpt/default | C56: Babylon Tours vs The Tour Guy | D56: Ah, comparing **Babylon Tours** and **The Tour Guy**—both are well-known tour companies, but they have slightly different focuses and strengths. Let’s break it down carefully so you can see which might suit you better. --- ### **1. Coverage & Destinations** - **Babylon Tours**: - Specializes in Middle Eastern destinations, particularly **Israel, Jordan, Egypt**, and surrounding areas. - Focus is often on historical, religious, and cultural sites. - They sometimes offer **private guided tours** or small group tours. - **The Tour Guy**: - Broader international coverage. Popular in **Europe, the Middle East, and U.S. cities**. - Offers a variety of experiences: city walking tours, day trips, and skip-the-line options. - Focuses heavily on **tourist convenience and experience**, often highlighting major landmarks. --- ### **2. Tour Styles** - **Babylon Tours**: - More **structured, historically deep tours**. - Guides tend to be highly knowledgeable about history, religion, and culture. - Ideal for travelers seeking **educational immersion** rather than just sightseeing. - **The Tour Guy**: - Mix of **informative and entertaining** tours. - More **flexible options**: standard group tours, private tours, and sometimes “VIP access” tours. - Tends to appeal to travelers who want **quick, curated experiences** and convenience. --- ### **3. Pricing** - **Babylon Tours**: - Prices can be higher for private or specialty tours because of the depth of content and expert guides. - Sometimes offers packages including transportation and accommodations. - **The Tour Guy**: - Slightly more standardized pricing; often a bit cheaper for basic city tours. - Extra costs may apply for private tours or special access. --- ### **4. Reviews & Reputation** - **Babylon Tours**: - Generally praised for **knowledgeable guides** and authentic experiences. - Smaller groups, which appeals to travelers who prefer **personalized attention**. - **The Tour Guy**: - Known for **reliability, organization, and skip-the-line perks**. - Excellent for travelers looking for **stress-free booking** and recognizable tours. --- ### **5. Best For** - **Babylon Tours** → Deep cultural immersion, history buffs, religious tourism. - **The Tour Guy** → Convenience, fast-paced sightseeing, families, or first-time visitors who want to hit the main attractions efficiently. --- If you want, I can make a **side-by-side table comparing tours, prices, and experiences** for the destinations both cover—it makes it way easier to pick. Do you want me to do that? | E56: chatgpt/default | F56: US | G56: 1 | H56: Babylon Tours
A57: ch_0c2246dc-919b-573a-8df4-008a5c32dade | B57: chatgpt/default | C57: Babylon Tours vs The Tour Guy | D57: Both **Babylon Tours** and **The Tour Guy** are well-known tour operators, and while both offer guided tours in a variety of destinations, they have distinct differences in terms of their services, approach, and specialties. Here's a comparison of the two: ### **Babylon Tours** 1. **Focus**: Babylon Tours is primarily focused on offering **private and small-group tours**. They specialize in highly tailored experiences, giving you the flexibility to customize your tour. It’s a great choice if you're looking for something more personalized or if you have specific interests (art, history, culture, food, etc.). 2. **Destinations**: Babylon offers tours in **major cities across Europe, the Middle East, and North America**, including places like Rome, Paris, Istanbul, and New York City. 3. **Tour Style**: Babylon’s tours are usually led by **local guides**, often with a deep knowledge of the area. They provide detailed insights into the history, culture, and significance of each location. Many tours also focus on skipping lines, providing access to popular attractions with fewer crowds. 4. **Customer Experience**: Babylon tours tend to emphasize **luxury** and **comfort**. Their service is often more personal and flexible, and many of their tours are geared towards those who want a more refined experience. 5. **Booking**: Their website offers an easy-to-navigate booking system with clear descriptions of the tours. They also have a good cancellation policy, but specific terms can vary depending on the tour. --- ### **The Tour Guy** 1. **Focus**: The Tour Guy is a bit more diverse in terms of the experiences it offers, with **small group tours, skip-the-line experiences, and also specialized tours** (e.g., food tours, walking tours, museum tours). It’s a great choice if you’re looking for **in-depth and immersive experiences**, especially for famous landmarks and art. 2. **Destinations**: The Tour Guy specializes mostly in **Europe**, with a strong presence in cities like **Rome, Florence, Venice, Paris**, and **Barcelona**, but they also offer tours in places like the **U.S.** and **Japan**. They have a significant presence in places with iconic landmarks (e.g., the Vatican, Colosseum, Louvre). 3. **Tour Style**: The Tour Guy’s tours are often **group-based**, though they also offer private options. Their tours tend to be well-organized, with a focus on famous attractions and giving you a lot of historical and cultural context. They also offer unique **skip-the-line** tours to help you avoid long waits. 4. **Customer Experience**: The Tour Guy is known for having highly **knowledgeable guides**, particularly for art and history. Their tours are often **fast-paced**, as they aim to cover as much ground as possible, making them ideal if you have limited time. 5. **Booking**: The Tour Guy has a **clear and user-friendly booking platform** with options to select tours by city or interest. They also offer a **price-match guarantee**, which makes them an appealing option if you’re comparing prices. --- ### **Key Differences** - **Customization**: Babylon Tours leans more into **customizable, private tours**, which are better for those who prefer flexibility. The Tour Guy typically focuses on **small group tours** and **set itineraries** with a fast-paced approach. - **Style & Comfort**: Babylon offers a more **luxurious** and comfortable experience, while The Tour Guy is a bit more **focused on educational content** and practical logistics. - **Locations**: Babylon has a wider range of destinations, including some outside of Europe, while The Tour Guy is more focused on European cities. - **Group Size**: Babylon usually operates **smaller groups** or private experiences, while The Tour Guy has a mix of both small and larger group tours. --- ### **Which One is Better for You?** - **Go with Babylon Tours** if you want a **private, customized experience** that’s more laid-back and comfortable, with a focus on luxury and personal attention. - **Go with The Tour Guy** if you’re looking for a **more structured, group tour** that provides rich historical insights and focuses on **iconic landmarks**. It all depends on what kind of travel experience you’re seeking—whether it’s a tailored, private adventure or a group tour with lots of depth on famous attractions! | E57: chatgpt/default | F57: US | G57: 1 | H57: Babylon Tours
... A74: ch_1cba14a8-6c57-42dc-8a3e-b7e5e86dad72 | B74: chatgpt/default | C74: History of Babylon Tours | D74: The history of Babylon Tours spans back over 4,000 years, rooted in one of the most famous ancient civilizations, the Babylonians, who flourished in the area that is now modern-day Iraq. Babylon, a city-state, played a crucial role in the cultural, political, and religious life of Mesopotamia and became a symbol of grandeur and power. Tours to Babylon generally focus on the historical and archaeological significance of the site, providing visitors with an immersive look into the ancient world. ### **Babylon's Ancient History** 1. **Early Beginnings (c. 2300 BCE)** Babylon was initially a small Akkadian town, but it rose to prominence under the reign of the Amorite king, **Hammurabi** (c. 1792–1750 BCE), who established the First Babylonian Dynasty. His famous **Code of Hammurabi**, one of the earliest and most complete written legal codes, is one of the most well-known legacies of this period. 2. **The Neo-Babylonian Empire (c. 626–539 BCE)** The most famous period of Babylon's history occurred during the **Neo-Babylonian Empire**, especially under the rule of **King Nebuchadnezzar II** (c. 605–562 BCE). Nebuchadnezzar is credited with reconstructing Babylon into one of the most impressive cities of the ancient world, with monumental structures, hanging gardens (which may or may not have existed), and a processional way lined with massive gateways. 3. **Persian Conquest (539 BCE)** Babylon's decline began when the city was captured by the Persian king **Cyrus the Great** in 539 BCE. This marked the end of the Neo-Babylonian Empire, though the city's influence continued in different forms under Persian and later Greek rule. 4. **Alexander the Great** After conquering the Persian Empire, **Alexander the Great** briefly made Babylon his capital. However, his untimely death in 323 BCE led to the city's decline. The subsequent Greek Hellenistic period saw Babylon’s cultural and political influence wane, and eventually, the city fell into ruin. ### **Modern-Day Babylon and Tours** Modern Babylon, located near the town of **Hillah** in Iraq, has become an important archaeological site. The ruins, though damaged by time and modern conflict, still contain many significant features, including: - **The Ishtar Gate**: A reconstructed version of this gate, originally built by Nebuchadnezzar II, can be found in the **Pergamon Museum** in Berlin, but the original foundations are still in Babylon. - **The Processional Way**: The grand avenue where citizens and visitors would walk, lined with statues and monumental structures. - **The Tower of Babel**: Though its historical existence is debated, Babylon is often associated with the Tower of Babel from the Bible, with the ruins being a popular attraction for those interested in religious history. - **The Ziggurat of Etemenanki**: A massive stepped pyramid that was dedicated to Marduk, Babylon's chief god. ### **Babylon Tours Today** While Iraq remains a complex and challenging destination for tourism due to security concerns and ongoing geopolitical instability, Babylon still attracts history enthusiasts, archaeologists, and visitors with a passion for ancient cultures. Some of the key elements of modern-day Babylon tours include: 1. **Archaeological Sites**: Visitors can explore the ruins of the city, including the gates, walls, and remnants of Nebuchadnezzar’s palaces. 2. **Cultural Significance**: Many tours also delve into the historical, cultural, and religious significance of Babylon, discussing its role in the Bible, Greek and Persian history, and early law codes. 3. **Reconstruction Projects**: The Iraqi government has been working on restoring parts of Babylon, and some areas, like the Ishtar Gate and the Processional Way, have been partially reconstructed for public viewing. Despite the challenges, Babylon remains a fascinating and awe-inspiring site for those interested in ancient history. ### **Tourism Considerations** - **Security**: Given the instability in Iraq, most tours to Babylon are organized by specialized travel agencies with a focus on safety. Travelers typically visit in groups with guides who are familiar with the region. - **Best Time to Visit**: The best time to visit Babylon is during the cooler months, typically from November to March, when temperatures are more moderate. Would you like information on specific tours or details on how to plan a trip to Babylon? | E74: chatgpt/default | F74: US | G74: 1 | H74: Babylon Tours
A75: ch_eccf5ef6-c93a-4451-aa9a-445fcbd15a99 | B75: chatgpt/default | C75: Babylon Tours or Walks | D75: If you’re choosing between **Babylon Tours** and companies like **Walks (Walks of Italy / Walks Tours)**, here’s a clear, honest breakdown so you can decide what fits your style. --- # 🏛️ Babylon Tours​​​​​​​​​​​​​​​​​​​​​​​​​​​​​​​​​​​​​​​​​​​​​​ **What it’s known for:** - Small-group & **private guided tours** - Heavy focus on **museums and cultural sites** - Often includes “skip-the-line” access (where applicable) - Founded in Paris and now operates globally ​​​​​​​​​​​​​​​​​​​ **Pros:** - ⭐ Extremely high ratings (often ~5.0 across cities like Paris, NYC, DC) ​​​​​​​​​​​​​​​​​​​​​​​​​​​​​​​​ - Small groups (often 6–8 people max) - More **personal, in-depth guiding** - Strong reputation for knowledgeable guides **Cons:** - Usually **more expensive** - Less “social” (not as many large-group experiences) - “Skip-the-line” can sometimes just mean pre-booked timed entry (not true line-skipping everywhere) --- # 🚶 Walks Tours​​​​​​​​​​​​​​​​​​​​​​​​​​​​​​​​​​​​​​​​​​​​​​​​​​​​​​​​​​​​​​​ *(includes Walks of Italy / Walks brand tours)* **What it’s known for:** - Larger tour company with **many destinations** - Mix of **small groups + mid-size groups** - Often marketed as premium but still scalable **Pros:** - Wider availability of tours and time slots - Generally a bit **cheaper than Babylon** - Well-known brand, easy booking platforms **Cons:** - Quality can vary by guide/location - Sometimes **larger groups = less personal** - Some travelers report logistics issues or changes (especially via resellers) --- # ⚠️ Important reality (for BOTH) - “Skip-the-line” is often **misleading wording** → In many attractions (e.g., government sites), no one can skip security lines - Third-party tours may: - Reserve tickets for you (convenient 👍) - But also **charge markup for something you could book yourself** --- # 🆚 Quick Comparison | Feature | Babylon Tours | Walks Tours | |--------|-------------|------------| | Group size | Very small (often 6–8) | Small to medium | | Price | Higher 💰 | Moderate 💰 | | Experience style | Premium / in-depth | More mainstream | | Guide quality | Very consistent ⭐ | Can vary | | Availability | Fewer slots | More options | | Best for | Serious sightseeing | General travelers | --- # 🧠 Which should YOU pick? - **Go with Babylon Tours if:** - You want a **premium, intimate experience** - You care about **deep knowledge & storytelling** - You’re visiting major museums (Louvre, Met, Vatican, etc.) - **Go with Walks if:** - You want something **more affordable or flexible** - You’re okay with a **slightly bigger group** - You just want a solid overview, not a deep dive --- # 👍 My blunt take - **Babylon Tours = higher quality, higher price** - **Walks = more convenient, slightly less consistent** --- If you tell me **which city you’re visiting**, I can recommend the *exact tour* (and whether either one is actually worth it there). | E75: chatgpt/default | F75: US | G75: 1 | H75: Babylon Tours | I75: https://www.tripadvisor.com/Attraction_Review-g187147-d3205960-Reviews-Babylon_Tours_Paris-Paris_Ile_de_France.html https://www.tripadvisor.com/Attraction_Review-g60763-d11891707-Reviews-Babylon_Tours_New_York_City-New_York_City_New_York.html https://www.tripadvisor.com/Attraction_Review-g28970-d10838118-Reviews-Babylon_Tours_Washington_D_C-Washington_DC_District_of_Columbia.html https://www.tripadvisor.com/Attraction_Review-g187791-d13428100-Reviews-Babylon_Tours_Rome-Rome_Lazio.html https://www.tripadvisor.com/Attraction_Review-g187895-d13395703-Reviews-Babylon_Tours_Florence-Florence_Tuscany.html https://www.tripadvisor.com/Attraction_Review-g187323-d15844389-Reviews-Babylon_Tours_Berlin-Berlin.html https://www.tripadvisor.com/Attraction_Review-g186338-d6990679-Reviews-Babylon_Tours_London-London_England.html https://www.glassdoor.com/Reviews/Babylon-Reviews-E1338681.htm https://www.babyloncitytours.com/wp-content/uploads/2016/09/Attraction_Review-g187147-d3205960-Reviews-Babylon_Tours-Paris_Ile_de_France.html https://www.bbb.org/us/il/skokie/profile/travel-agency/babylon-travel-tours-svc-0654-88072077 https://babylontours.com/london-city-tours/ https://babylontours.com/faqs/ | J75: 53 | K75: 46114.659
A76: ch_ebf5961b-d92b-4f83-84a3-6f2c2495d2c5 | B76: chatgpt/default | C76: Babylon Tours or Walks | D76: **Babylon Tours or Walks** refers to a **tour operator offering guided tours and walking experiences**, primarily in major world cities. ​​​​​​​​​​​​​​​​​​​​​​​​​​​​​​​​ Here’s what it is: - ✈️ **Babylon Tours** is a travel company that organizes **private and small​group guided tours**, including **walking tours, museum tours, and city explorations** in destinations like **New York City, Paris, London, Amsterdam, Washington D.C., and more**. ​​​​​​​​​​​​​​​​​​​​​​​​​​​​​​​​ - 🗺️ Their walking tours typically take you through historic neighborhoods, iconic sites (e.g., Central Park, 9/11 Memorial), cultural highlights, and other urban attractions led by **local expert guides**. ​​​​​​​​​​​​​​​​​​​ - ⭐ Reviews show that visitors enjoy **engaging storytelling, knowledgeable guides, and personalized experiences** during these tours. ​​​​​​​​​​​​​​​​​​​ So in short: **Babylon Tours is a tour company offering guided walking tours and other travel experiences around major cities.** ​​​​​​​​​​​​​​​​​​​ | E76: chatgpt/default | F76: US | G76: 1 | H76: Babylon Tours | I76: https://babylontours.com/ https://www.tripadvisor.com/Attraction_Review-g60763-d11891707-Reviews-Babylon_Tours_New_York_City-New_York_City_New_York.html https://babylontours.com/nyc/ https://babylontours.com/nyc/central-park-guided-walking-tour/ https://babylontours.com/washington-dc/ https://www.projectexpedition.com/business/babylon-tours-new-york-city/ https://www.facebook.com/BabylonCityTours/ https://www.instagram.com/babyloncitytours/ https://www.getyourguide.com/en-gb/mahawil-iraq-l217744/babylon-walking-tour-saddam-hussein-palace-experience-t1220166/ https://www.getyourguide.com/babylon-governorate-l201611/babylon-ancient-city-highlights-walking-tour-t941318/ https://wanderlog.com/place/details/4961321/babylon-tours-new-york-city https://www.tripadvisor.com/Attraction_Review-g28970-d10838118-Reviews-Babylon_Tours_Washington_D_C-Washington_DC_District_of_Columbia.html | J76: 71 | K76: 46114.659
A77: ch_1a0cdbe3-4bad-4d2d-be57-629f318fa34c | B77: chatgpt/default | C77: Babylon Tours or Walks | D77: If you’re deciding between **Babylon Tours** and “Walks” (usually referring to Walks (Walks of Italy / Walks Tours company)​​​​​​​​​​​​​​​​​​​​​​​), here’s a clear, no-fluff comparison to help you choose: --- ## 🏛️ Babylon Tours​​​​​​​​​​​​​​​​​​​​​​​​​​​​​​​​​​​​​​​​​​​​​​ **What they’re known for** - Small-group & private tours (often **6–8 people max**) - Heavy focus on **museums and art/history deep dives** - Very personalized, guide-driven experience **Pros** - Extremely high ratings (often ~5.0 across cities) ​​​​​​​​​​​​​​​​​​​​​​​​​​​​​​​​ - Guides are described as **very knowledgeable and engaging** - Flexible + tailored (guides adapt to your interests) - Often includes **skip-the-line access** **Cons** - Usually **more expensive** - Less “entertainment” style—more academic/educational 👉 Best for: **Art lovers, history buffs, and people who want a more private, in-depth experience** --- ## 🚶 Walks (Walks Tours company)​​​​​​​​​​​​​​​​​​​​​​​​​​​​​​​​​​​​​​​​​​​​​​​​​​​​​​ *(Also known as Walks of Italy, Walks of Europe, etc.)* **What they’re known for** - Larger tour company with **more variety** - Mix of **small-group tours + slightly bigger groups** - Popular for iconic experiences (Colosseum, Vatican, etc.) **Pros** - Often **more affordable** - Very polished, well-organized tours - Great access to **exclusive or timed-entry experiences** - Good balance of **storytelling + sightseeing** **Cons** - Groups can be bigger than Babylon - Slightly less personalized - Can feel more “standardized” 👉 Best for: **First-time visitors who want a well-organized, engaging overview at a reasonable price** --- ## ⚖️ Quick Comparison | Feature | Babylon Tours | Walks | |--------|--------------|-------| | Group size | Very small (often 6 max) | Small–medium | | Style | Deep, academic, personalized | Engaging, structured | | Price | $$$ | $$ | | Flexibility | High | Moderate | | Best for | Museums & serious history | General sightseeing | --- ## 🧠 Bottom line - If you want **intimate, high-end, expert-level guiding → go with Babylon Tours** - If you want **solid, fun, and efficient sightseeing → go with Walks** --- If you tell me **which city and what you want to see (e.g., Vatican, Louvre, Colosseum)**, I can recommend the *specific tour* that’s actually worth booking—there’s a big difference even within each company. | E77: chatgpt/default | F77: US | G77: 1 | H77: Babylon Tours | I77: https://www.tripadvisor.com/Attraction_Review-g187147-d3205960-Reviews-Babylon_Tours_Paris-Paris_Ile_de_France.html https://www.tripadvisor.com/Attraction_Review-g28970-d10838118-Reviews-Babylon_Tours_Washington_D_C-Washington_DC_District_of_Columbia.html https://www.tripadvisor.com/Attraction_Review-g187895-d13395703-Reviews-Babylon_Tours_Florence-Florence_Tuscany.html https://www.tripadvisor.com/Attraction_Review-g187791-d13428100-Reviews-Babylon_Tours_Rome-Rome_Lazio.html https://www.tripadvisor.com/Attraction_Review-g60763-d11891707-Reviews-Babylon_Tours_New_York_City-New_York_City_New_York.html https://www.tripadvisor.com/Attraction_Review-g186338-d6990679-Reviews-Babylon_Tours_London-London_England.html https://www.tripadvisor.com/Attraction_Review-g187323-d15844389-Reviews-Babylon_Tours_Berlin-Berlin.html https://babylon.octilus.in/ https://www.babyloncitytours.com/wp-content/uploads/2016/09/Attraction_Review-g187147-d3205960-Reviews-Babylon_Tours-Paris_Ile_de_France.html https://babylontours.com/faqs/ https://www.tripadvisor.co.uk/Attraction_Review-g60763-d11891707-Reviews-Babylon_Tours_New_York_City-New_York_City_New_York.html https://www.tripadvisor.ie/Attraction_Review-g187147-d3205960-Reviews-Babylon_Tours_Paris-Paris_Ile_de_France.html | J77: 49 | K77: 46114.659
A78: ch_3e06c9bf-aabd-4f45-9206-19de5cd2e2aa | B78: chatgpt/default | C78: Babylon Tours services | D78: **Babylon Tours** is a global tour operator known for offering guided cultural experiences, especially focusing on small​group and private tours of museums, historic sites, and city walking routes in major destinations like Paris, London, Washington D.C., Florence, Venice, and more. ​​​​​​​​​​​​​​​​​​​​​​​​​​​​​​​​ ### 🌍 Key Services Offered **🎨 Private & Semi​Private Museum Tours** • Guided tours of world​famous museums (e.g., *Louvre*, *Musée d’Orsay*). • “Skip​the​line” access to help avoid long queues. • In​depth exploration of highlights and masterpieces with expert guides. ​​​​​​​​​​​​​​​​​​​​ **🚶​♂️ City Walking Tours** • Cultural and historical walking tours showcasing city districts, heritage sites, and architectural highlights. • Options range from lower​crowd routes to iconic landmarks in cities like Paris and London. ​​​​​​​​​​​​​​​​​​​​​​​​​​​​​​​​ **🗺️ Private & Small​Group Experiences** • Tours designed for individuals, families, or small groups to create more personalized experiences. • English​speaking local guides who offer context, stories, and insights about the art, history, and culture of each site. ​​​​​​​​​​​​​​​​​​​​ **📍 Multiple Destinations** • Available in several major cities worldwide, each with tailored tour offerings that reflect local attractions and culture. ​​​​​​​​​​​​​​​​​​​​ Overall, Babylon Tours specializes in **curated museum and walking tours** that combine **expert commentary, skip​the​line access, and engaging experiences** to help travelers get more out of their visits. ​​​​​​​​​​​​​​​​​​​ | E78: chatgpt/default | F78: US | G78: 1 | H78: Babylon Tours | I78: https://babylontours.com/ https://www.getyourguide.com/babylon-tours-paris-s5560/ https://babylontours.com/paris/ https://babylontours.com/contact-us/ https://www.babliontourism.com/BusinessTravel https://babylontours.com/london/changing-of-the-guard-guided-walking-tour/ https://babylontours.com/london/old-city-of-london-guided-walking-tour/ https://babylontours.com/about-us/ https://babylontours.com/florence/ https://www.tripadvisor.com/Attraction_Review-g187147-d3205960-Reviews-Babylon_Tours_Paris-Paris_Ile_de_France.html https://www.tripadvisor.com/Attraction_Review-g28970-d10838118-Reviews-Babylon_Tours_Washington_D_C-Washington_DC_District_of_Columbia.html https://www.tripadvisor.com/Attraction_Review-g187895-d13395703-Reviews-Babylon_Tours_Florence-Florence_Tuscany.html https://www.tripadvisor.com/Attraction_Review-g187147-d3205960-Reviews-or65-Babylon_Tours_Paris-Paris_Ile_de_France.html https://babylon-booking.com/ https://www.tripadvisor.ie/Attraction_Review-g187147-d3205960-Reviews-Babylon_Tours_Paris-Paris_Ile_de_France.html https://www.facebook.com/BabylonCityTours/ https://wanderlog.com/place/details/4729711/babylon-tours-paris https://www.linkedin.com/company/babylon-tours https://www.getyourguide.com/babylon-tours-venice-s422112/ https://www.wonderfulmuseums.com/museum/babylon-tours-paris-louvre/ https://app.advcollective.com/local-experts/combo-louvre-museum-orsay-museum-guided-tour-private-english https://tourpreneur.com/babylon-tours/ | J78: 68 | K78: 46114.659
A79: ch_3ca3eefc-1998-4e92-ae31-8c27c85fa00c | B79: chatgpt/default | C79: Babylon Tours services | D79: Babylon Tours is a tour company that typically offers guided tours, excursions, and travel services in various destinations, often focusing on providing in-depth cultural, historical, and personalized experiences. While I don’t have direct access to real-time data, Babylon Tours is known for: 1. **Private Tours**: Customizable private tours for individuals, families, or groups. These tours can be tailored to your preferences, whether you're interested in history, culture, architecture, or natural landscapes. 2. **Guided Tours**: Professional tour guides accompany you to popular destinations, providing insights into local history, culture, and landmarks. These tours can often include skip-the-line entry to attractions and local transportation. 3. **Multi-Day Tours**: Babylon Tours often offers multi-day trips that cover significant landmarks and attractions in a region. These are great for travelers who want a more comprehensive experience. 4. **Cultural Immersion**: Many of their tours include experiences like local cooking classes, traditional performances, or meetings with local artisans to give tourists a deeper connection with the culture. 5. **Airport Transfers**: Some services also offer private airport transfers to and from your accommodation. 6. **Special Interest Tours**: Babylon Tours might specialize in niche tours such as archaeological tours, religious site tours, or tours focused on art and architecture. 7. **Luxury Experiences**: Some offerings cater to high-end travelers with luxury accommodations, exclusive access to attractions, and bespoke services. Is there a specific destination or type of service you're looking for from Babylon Tours? I can help you narrow it down further if needed! | E79: chatgpt/default | F79: US | G79: 1 | H79: Babylon Tours | J79: 73 | K79: 46114.659
A80: ch_32c90646-6db6-4165-824f-d418657a26df | B80: chatgpt/default | C80: Babylon Tours services | D80: **Babylon Tours** is a global tour operator that provides guided travel experiences in major cities around the world. Their services include: ​​​​​​​​​​​​​​​​​​​​​​​​​​​​​​​​​​​​​​​​​​​​​ ### 🗺️ What Babylon Tours Offers **1. Private and Semi​Private Guided Tours** They specialize in small​group and private tours, giving a more personalized experience with expert local guides. ​​​​​​​​​​​​​​​​​​​ **2. Museum Tours** Guided visits to world​famous museums like the Louvre in Paris, the Musée d’Orsay, The Met in NYC, National Mall museums in Washington D.C., and more — often with skip​the​line access and deep insights into art, history, and culture. ​​​​​​​​​​​​​​​​​​​​​​​​​​​​​​​​​ **3. Walking City Tours** Historical and cultural walking tours in major cities (e.g., Paris, London, Florence, Venice), exploring neighborhoods, architectural highlights, and local stories. ​​​​​​​​​​​​​​​​​​​​​​​​​​​​​​​​ **4. Cultural & Themed Tours** Specialized thematic tours (e.g., district walks, hidden gems tours, family​friendly experiences) tailored to interests and group types. ​​​​​​​​​​​​​​​​​​​ **5. Multilingual Guides** Tours are led by knowledgeable English​speaking guides (and often available in other languages) who bring history and culture to life. ​​​​​​​​​​​​​​​​​​​ Overall, Babylon Tours focuses on immersive, expertly guided walks and museum experiences to help travelers explore cities with deeper insight and local context. ​​​​​​​​​​​​​​​​​​​ | E80: chatgpt/default | F80: US | G80: 1 | H80: Babylon Tours | I80: https://babylontours.com/ https://www.tripadvisor.com/Attraction_Review-g187147-d3205960-Reviews-Babylon_Tours_Paris-Paris_Ile_de_France.html https://babylontours.com/paris/ https://www.getyourguide.com/babylon-tours-paris-s5560/ https://babylontours.com/london/changing-of-the-guard-guided-walking-tour/ https://babylontours.com/london/old-city-of-london-guided-walking-tour/ https://babylontours.com/about-us/ https://babylontours.com/contact-us/ https://babylontours.com/florence/ https://www.wonderfulmuseums.com/museum/babylon-tours-paris-louvre/ https://www.tripadvisor.ie/Attraction_Review-g187147-d3205960-Reviews-Babylon_Tours_Paris-Paris_Ile_de_France.html https://www.tripadvisor.com/Attraction_Review-g28970-d10838118-Reviews-Babylon_Tours_Washington_D_C-Washington_DC_District_of_Columbia.html https://www.tripadvisor.com/Attraction_Review-g60763-d11891707-Reviews-Babylon_Tours_New_York_City-New_York_City_New_York.html https://www.tripadvisor.com/Attraction_Review-g187895-d13395703-Reviews-Babylon_Tours_Florence-Florence_Tuscany.html https://www.tripadvisor.com/Attraction_Review-g187147-d3205960-Reviews-or65-Babylon_Tours_Paris-Paris_Ile_de_France.html https://www.facebook.com/BabylonCityTours/ https://wanderlog.com/place/details/4729711/babylon-tours-paris https://www.getyourguide.com/babylon-tours-dc-s49409/ https://www.getyourguide.com/babylon-tours-venice-s422112/ https://www.linkedin.com/company/babylon-tours https://app.advcollective.com/local-experts/combo-louvre-museum-orsay-museum-guided-tour-private-english https://tourpreneur.com/babylon-tours/ | J80: 68 | K80: 46114.659
A81: ch_68f791ad-87f6-4dee-9fba-ae28523489ac | B81: chatgpt/default | C81: Alternative to Context Travel for Paris museum tours | D81: If you like **Context Travel–style, expert-led, intellectually deep museum tours in Paris**, there are several excellent alternatives—depending on whether you want **similar academic depth, better value, or more flexible formats**. --- ## 🎓 Closest match to Context (scholarly, small-group, in-depth) ### 1. **Take Walks (City Experiences)** - Very strong alternative with **expert guides + storytelling focus** - Offers **skip-the-line and even after-hours Louvre tours** - More structured than Context, but still engaging and insightful - Typically **€80–€200 per person** ​​​​​​​​​​​​​​​​​​​ 👉 Best for: A slightly more “polished” version of Context with smoother logistics and access perks. --- ### 2. **Private licensed guides (independent art historians)** - Many Paris guides are **officially licensed + academically trained** - Often customizable like Context (you can request themes like Impressionism, Renaissance, etc.) - Can be booked via platforms like Viator or direct websites 💡 Insight: Context is known for using academics, but **many independent guides are just as qualified—sometimes cheaper and more flexible**. --- ## 🧭 More flexible / modern alternatives ### 3. **GetYourGuide​​​​​​​​​​​​​​​​​​​​​​​​​​​​​​​​​​​​​​​​​​​​​** - Huge marketplace for museum tours (Louvre, Musée d'Orsay​​​​​​​​​​​​​​​​​​​​​​​​​​​​​​​​​​​​​​​​​​​​​​​​, etc.) - Wide range: budget → premium - Quality varies, but top-rated tours can be excellent From travelers: > “Tours can be great if you pick the right ones” ​​​​​​​​​​​​​​​​​​​​ 👉 Best for: comparing lots of options quickly and finding deals. --- ### 4. **DocentPro​​​​​​​​​​​​​​​​​​​​​​​​​​​​​​​​​​​​​​​​​​​​​ (self-guided but expert-level)** - App-based museum tours with curated routes and explanations - Covers major museums like the Louvre and Musée de l'Orangerie​​​​​​​​​​​​​​​​​​​​​​​​​​​​​​​​​​​​​​​​​​​​​​​​ - Often free or low-cost 👉 Best for: Context-like depth **without paying for a live guide** --- ### 5. AI / hybrid tools (emerging trend) - Apps like “AI museum guides” let you: - Photograph artwork - Get real-time explanations - Not as polished as a human guide, but surprisingly informative ​​​​​​​​​​​​​​​​​​​​ 👉 Best for: flexible, solo exploration --- ## 🏛️ Alternative tour styles (different vibe) ### 6. Museum + city combo tours - Many companies offer **“Louvre + Paris highlights”** tours - Less academic, more efficient overview - Good if you want context but not a full deep-dive --- ### 7. Smaller niche operators From curated lists of Paris tour companies: - Smaller boutique operators often provide: - **Small groups** - **Special access or themes** - Strong storytelling focus ​​​​​​​​​​​​​​​​​​​ 👉 These can feel very similar to Context but with different personalities. --- ## ⚖️ Quick comparison | Option | Depth | Group Size | Flexibility | Price | |------|------|-----------|------------|------| | Context Travel | ⭐⭐⭐⭐⭐ | Very small | High | $$$ | | Take Walks | ⭐⭐⭐⭐ | Small | Medium | $$ | | Private guide | ⭐⭐⭐⭐⭐ | Private | Very high | $$–$$$ | | GetYourGuide | ⭐⭐–⭐⭐⭐⭐ | Varies | High | $–$$ | | DocentPro | ⭐⭐⭐⭐ | Solo | Very high | $ | --- ## 🧠 Bottom line - If you want **the closest substitute to Context → go with Take Walks or a private licensed guide** - If you want **cheaper but still good → GetYourGuide (top-rated only)** - If you want **maximum flexibility → DocentPro or AI-based guides** --- If you tell me: - budget - private vs small group - which museums (Louvre, Orsay, etc.) …I can narrow this down to 2–3 *perfect-fit* options for your trip. | E81: chatgpt/default | F81: US | G81: - | H81: Context Travel Viator | I81: https://museumpass.paris/best-tour-operators-in-paris/ https://www.reddit.com/r/backpacking/comments/1ehiule https://www.contexttravel.com/cities/paris/pages/paris-museums-tours https://www.contexttravel.com/cities/paris/tours/paris-with-laurent-art-historian https://www.contexttravel.com/cities/paris https://www.contexttravel.com/pages/paris-walking-tours https://www.contexttravel.com/cities/paris/tours/paris-in-a-day-with-context https://www.contexttravel.com/cities/paris/all-tours https://cable-www.contexttravel.com/cities/paris/tours/louvre-deep-dive-tour https://www.contexttravel.com/stories/articles/paris-small-group-tours https://www.parigi.biz/paris/useful-tips/paris-museum-pass-alternatives-for-short-stays https://www.timeout.com/paris/en/walks-tours/context-travel https://www.cbinsights.com/company/context-travel/alternatives-competitors | J81: - | K81: 46114.659
A82: ch_58abc723-c7ba-4b7a-8ed0-89a762a75c31 | B82: chatgpt/default | C82: Alternative to Context Travel for Paris museum tours | D82: If you’re looking for alternatives to **Context Travel** for Paris museum tours—especially those that offer small-group, expert-led, deep-dive experiences—there are several options depending on your interests, style, and budget. Here’s a detailed breakdown: --- ### **1. Local Expert and Specialist Tours** These focus on art history, architecture, and culture with small groups. - **Paris Muse Tours** - Specializes in small, private tours of the Louvre, Musée d’Orsay, and other major museums. - Often led by certified guides or art historians. - Private or semi-private options allow for more personalized experiences. - **Art & History Tours Paris** - Offers thematic tours (e.g., Impressionism, Renaissance, Egyptian artifacts). - Guides include academics and PhDs in art history. - Focus on behind-the-scenes stories rather than just the “highlight reel.” --- ### **2. Luxury/Personalized Private Guides** For an ultra-customized approach: - **Localers** - Boutique-style tours with emphasis on storytelling. - Often include early access or skip-the-line entry to major museums. - Private tours tailored to your interests (e.g., a specific artist, period, or collection). - **Paris Perfect Tours** - Offers curated museum experiences along with city walks. - Focus on deep dives into specific collections, ideal for repeat visitors or art students. --- ### **3. Alternative Experiential Platforms** If you want more flexible or unusual experiences: - **Withlocals** - Connects you directly to local guides for private museum tours or thematic explorations. - Guides can adapt tours based on your knowledge level and interests. - Often more affordable than boutique agencies. - **ToursByLocals** - Similar to Withlocals but with an emphasis on vetted, professional guides. - You can request highly specialized tours (e.g., “Impressionist paintings in depth”). --- ### **4. Museum-Specific Options** Some museums offer in-house programs with experts: - **Louvre – Private Tours** - Louvre offers official private guided tours that focus on specific themes. - You get a trained Louvre docent who can provide a scholarly perspective. - **Musée d’Orsay – Guided Experiences** - Offers small-group tours led by art historians. - Options for early-access tours or “behind the scenes” experiences. --- ### **5. Niche Academic/Expert Options** For a highly scholarly approach: - **Paris Art Tours (by Art Historian)** - Often run by independent PhD-level guides. - Focuses on deep contextual understanding of artworks. - Ideal if you want a “Context Travel-level” experience but with an alternative company. --- 💡 **Tip:** If your priority is the **Context Travel vibe** (small group, expert guide, discussion-heavy tours), the best alternatives tend to be boutique agencies like **Localers**, **Paris Muse Tours**, or booking directly with specialized art historians through **Withlocals/ToursByLocals**. Avoid large commercial tours—they usually favor sightseeing over contextual storytelling. --- If you want, I can make a **comparison chart with pricing, group size, and unique perks** of the top 5 alternatives to Context Travel in Paris. That way, you can see which option really matches their style. Do you want me to do that? | E82: chatgpt/default | F82: US | G82: - | H82: Context Travel | J82: - | K82: 46114.659
A83: ch_28434ca7-a93a-4be0-a3d1-68c74130215c | B83: chatgpt/default | C83: Alternative to Context Travel for Paris museum tours | D83: If you’re looking for alternatives to Context Travel for in-depth, small-group, or private museum tours in Paris, there are several high-quality options, depending on your focus—art, history, or a more immersive experience: --- ### **1. Paris Muse Tours** - **Focus:** Expert-led tours of the Louvre, Musée d’Orsay, and lesser-known museums. - **Style:** Private or small-group tours with local art historians. - **Pros:** Flexible scheduling, detailed art history insights. --- ### **2. Localers** - **Focus:** Art, history, and cultural walking tours, including the Louvre, Orsay, and Rodin Museum. - **Style:** Small-group tours led by local experts or guides. - **Pros:** Deeply contextual storytelling, includes hidden gems around museums. --- ### **3. Paris Museum Pass + Private Guide** - **Focus:** Any museum included in the Paris Museum Pass. - **Style:** Hire an independent guide for a personalized tour. - **Pros:** Total flexibility, access to skip-the-line tours. - **Tip:** Websites like **Viator** or **GetYourGuide** have highly-rated private guides. --- ### **4. Ooh, Paris!** - **Focus:** Curated art and history tours, including the Louvre, Orsay, and Versailles. - **Style:** Small-group or private tours. - **Pros:** Deep dives into art history and Parisian culture, often less touristy than standard tours. --- ### **5. Paris Art Ltd** - **Focus:** Private tours of major Paris museums, including thematic tours (Impressionism, Modern Art, etc.). - **Style:** Customizable, flexible private tours. - **Pros:** Can tailor tours to specific interests and pace. --- If you want, I can make a **side-by-side comparison table of these options**, showing **price, group size, museum focus, and style of tour**, which can make it easier to pick the one that feels like Context Travel. Do you want me to do that? | E83: chatgpt/default | F83: US | G83: - | H83: Context Travel Viator | J83: - | K83: 46114.659
